{
    "documents": [
        {
            "name": "Clear Metadata Field.md",
            "title": "Clear Metadata Field.md",
            "depth": 5,
            "order": 1,
            "is_dir": false,
            "icon": "",
            "status": 1,
            "filepath": "Ue/blueprint/en/USD/Metadata Utils/Clear Metadata Field.md",
            "url": "Ue/blueprint/en/USD/MetadataUtils/ClearMetadataField.md"
        },
        {
            "name": "Get Metadata Field.md",
            "title": "Get Metadata Field.md",
            "depth": 5,
            "order": 2,
            "is_dir": false,
            "icon": "",
            "status": 1,
            "filepath": "Ue/blueprint/en/USD/Metadata Utils/Get Metadata Field.md",
            "url": "Ue/blueprint/en/USD/MetadataUtils/GetMetadataField.md"
        },
        {
            "name": "Get Usd Asset User Data.md",
            "title": "Get Usd Asset User Data.md",
            "depth": 5,
            "order": 3,
            "is_dir": false,
            "icon": "",
            "status": 1,
            "filepath": "Ue/blueprint/en/USD/Metadata Utils/Get Usd Asset User Data.md",
            "url": "Ue/blueprint/en/USD/MetadataUtils/GetUsdAssetUserData.md"
        },
        {
            "name": "Has Metadata Field.md",
            "title": "Has Metadata Field.md",
            "depth": 5,
            "order": 4,
            "is_dir": false,
            "icon": "",
            "status": 1,
            "filepath": "Ue/blueprint/en/USD/Metadata Utils/Has Metadata Field.md",
            "url": "Ue/blueprint/en/USD/MetadataUtils/HasMetadataField.md"
        },
        {
            "name": "Set Metadata Field.md",
            "title": "Set Metadata Field.md",
            "depth": 5,
            "order": 5,
            "is_dir": false,
            "icon": "",
            "status": 1,
            "filepath": "Ue/blueprint/en/USD/Metadata Utils/Set Metadata Field.md",
            "url": "Ue/blueprint/en/USD/MetadataUtils/SetMetadataField.md"
        },
        {
            "name": "Set Usd Asset User Data.md",
            "title": "Set Usd Asset User Data.md",
            "depth": 5,
            "order": 6,
            "is_dir": false,
            "icon": "",
            "status": 1,
            "filepath": "Ue/blueprint/en/USD/Metadata Utils/Set Usd Asset User Data.md",
            "url": "Ue/blueprint/en/USD/MetadataUtils/SetUsdAssetUserData.md"
        }
    ],
    "categorys": []
}