{
    "documents": [
        {
            "name": "Apply Parameter Pack.md",
            "title": "Apply Parameter Pack.md",
            "depth": 4,
            "order": 1,
            "is_dir": false,
            "icon": "",
            "status": 1,
            "filepath": "Ue/blueprint/zh/Meta Sound Parameter Pack/Apply Parameter Pack.md",
            "url": "Ue/blueprint/zh/MetaSoundParameterPack/ApplyParameterPack.md"
        },
        {
            "name": "Get Bool.md",
            "title": "Get Bool.md",
            "depth": 4,
            "order": 2,
            "is_dir": false,
            "icon": "",
            "status": 1,
            "filepath": "Ue/blueprint/zh/Meta Sound Parameter Pack/Get Bool.md",
            "url": "Ue/blueprint/zh/MetaSoundParameterPack/GetBool.md"
        },
        {
            "name": "Get Float.md",
            "title": "Get Float.md",
            "depth": 4,
            "order": 3,
            "is_dir": false,
            "icon": "",
            "status": 1,
            "filepath": "Ue/blueprint/zh/Meta Sound Parameter Pack/Get Float.md",
            "url": "Ue/blueprint/zh/MetaSoundParameterPack/GetFloat.md"
        },
        {
            "name": "Get Int.md",
            "title": "Get Int.md",
            "depth": 4,
            "order": 4,
            "is_dir": false,
            "icon": "",
            "status": 1,
            "filepath": "Ue/blueprint/zh/Meta Sound Parameter Pack/Get Int.md",
            "url": "Ue/blueprint/zh/MetaSoundParameterPack/GetInt.md"
        },
        {
            "name": "Get Music Loop Configuration.md",
            "title": "Get Music Loop Configuration.md",
            "depth": 4,
            "order": 5,
            "is_dir": false,
            "icon": "",
            "status": 1,
            "filepath": "Ue/blueprint/zh/Meta Sound Parameter Pack/Get Music Loop Configuration.md",
            "url": "Ue/blueprint/zh/MetaSoundParameterPack/GetMusicLoopConfiguration.md"
        },
        {
            "name": "Get Music Seek Request.md",
            "title": "Get Music Seek Request.md",
            "depth": 4,
            "order": 6,
            "is_dir": false,
            "icon": "",
            "status": 1,
            "filepath": "Ue/blueprint/zh/Meta Sound Parameter Pack/Get Music Seek Request.md",
            "url": "Ue/blueprint/zh/MetaSoundParameterPack/GetMusicSeekRequest.md"
        },
        {
            "name": "Get Music Timestamp.md",
            "title": "Get Music Timestamp.md",
            "depth": 4,
            "order": 7,
            "is_dir": false,
            "icon": "",
            "status": 1,
            "filepath": "Ue/blueprint/zh/Meta Sound Parameter Pack/Get Music Timestamp.md",
            "url": "Ue/blueprint/zh/MetaSoundParameterPack/GetMusicTimestamp.md"
        },
        {
            "name": "Get String.md",
            "title": "Get String.md",
            "depth": 4,
            "order": 8,
            "is_dir": false,
            "icon": "",
            "status": 1,
            "filepath": "Ue/blueprint/zh/Meta Sound Parameter Pack/Get String.md",
            "url": "Ue/blueprint/zh/MetaSoundParameterPack/GetString.md"
        },
        {
            "name": "Get Trigger.md",
            "title": "Get Trigger.md",
            "depth": 4,
            "order": 9,
            "is_dir": false,
            "icon": "",
            "status": 1,
            "filepath": "Ue/blueprint/zh/Meta Sound Parameter Pack/Get Trigger.md",
            "url": "Ue/blueprint/zh/MetaSoundParameterPack/GetTrigger.md"
        },
        {
            "name": "Has Bool.md",
            "title": "Has Bool.md",
            "depth": 4,
            "order": 10,
            "is_dir": false,
            "icon": "",
            "status": 1,
            "filepath": "Ue/blueprint/zh/Meta Sound Parameter Pack/Has Bool.md",
            "url": "Ue/blueprint/zh/MetaSoundParameterPack/HasBool.md"
        },
        {
            "name": "Has Float.md",
            "title": "Has Float.md",
            "depth": 4,
            "order": 11,
            "is_dir": false,
            "icon": "",
            "status": 1,
            "filepath": "Ue/blueprint/zh/Meta Sound Parameter Pack/Has Float.md",
            "url": "Ue/blueprint/zh/MetaSoundParameterPack/HasFloat.md"
        },
        {
            "name": "Has Int.md",
            "title": "Has Int.md",
            "depth": 4,
            "order": 12,
            "is_dir": false,
            "icon": "",
            "status": 1,
            "filepath": "Ue/blueprint/zh/Meta Sound Parameter Pack/Has Int.md",
            "url": "Ue/blueprint/zh/MetaSoundParameterPack/HasInt.md"
        },
        {
            "name": "Has Music Loop Configuration.md",
            "title": "Has Music Loop Configuration.md",
            "depth": 4,
            "order": 13,
            "is_dir": false,
            "icon": "",
            "status": 1,
            "filepath": "Ue/blueprint/zh/Meta Sound Parameter Pack/Has Music Loop Configuration.md",
            "url": "Ue/blueprint/zh/MetaSoundParameterPack/HasMusicLoopConfiguration.md"
        },
        {
            "name": "Has Music Seek Request.md",
            "title": "Has Music Seek Request.md",
            "depth": 4,
            "order": 14,
            "is_dir": false,
            "icon": "",
            "status": 1,
            "filepath": "Ue/blueprint/zh/Meta Sound Parameter Pack/Has Music Seek Request.md",
            "url": "Ue/blueprint/zh/MetaSoundParameterPack/HasMusicSeekRequest.md"
        },
        {
            "name": "Has Music Timestamp.md",
            "title": "Has Music Timestamp.md",
            "depth": 4,
            "order": 15,
            "is_dir": false,
            "icon": "",
            "status": 1,
            "filepath": "Ue/blueprint/zh/Meta Sound Parameter Pack/Has Music Timestamp.md",
            "url": "Ue/blueprint/zh/MetaSoundParameterPack/HasMusicTimestamp.md"
        },
        {
            "name": "Has String.md",
            "title": "Has String.md",
            "depth": 4,
            "order": 16,
            "is_dir": false,
            "icon": "",
            "status": 1,
            "filepath": "Ue/blueprint/zh/Meta Sound Parameter Pack/Has String.md",
            "url": "Ue/blueprint/zh/MetaSoundParameterPack/HasString.md"
        },
        {
            "name": "Has Trigger.md",
            "title": "Has Trigger.md",
            "depth": 4,
            "order": 17,
            "is_dir": false,
            "icon": "",
            "status": 1,
            "filepath": "Ue/blueprint/zh/Meta Sound Parameter Pack/Has Trigger.md",
            "url": "Ue/blueprint/zh/MetaSoundParameterPack/HasTrigger.md"
        },
        {
            "name": "Make Metasound Parameter Pack.md",
            "title": "Make Metasound Parameter Pack.md",
            "depth": 4,
            "order": 18,
            "is_dir": false,
            "icon": "",
            "status": 1,
            "filepath": "Ue/blueprint/zh/Meta Sound Parameter Pack/Make Metasound Parameter Pack.md",
            "url": "Ue/blueprint/zh/MetaSoundParameterPack/MakeMetasoundParameterPack.md"
        },
        {
            "name": "Set Bool.md",
            "title": "Set Bool.md",
            "depth": 4,
            "order": 19,
            "is_dir": false,
            "icon": "",
            "status": 1,
            "filepath": "Ue/blueprint/zh/Meta Sound Parameter Pack/Set Bool.md",
            "url": "Ue/blueprint/zh/MetaSoundParameterPack/SetBool.md"
        },
        {
            "name": "Set Float.md",
            "title": "Set Float.md",
            "depth": 4,
            "order": 20,
            "is_dir": false,
            "icon": "",
            "status": 1,
            "filepath": "Ue/blueprint/zh/Meta Sound Parameter Pack/Set Float.md",
            "url": "Ue/blueprint/zh/MetaSoundParameterPack/SetFloat.md"
        },
        {
            "name": "Set Int.md",
            "title": "Set Int.md",
            "depth": 4,
            "order": 21,
            "is_dir": false,
            "icon": "",
            "status": 1,
            "filepath": "Ue/blueprint/zh/Meta Sound Parameter Pack/Set Int.md",
            "url": "Ue/blueprint/zh/MetaSoundParameterPack/SetInt.md"
        },
        {
            "name": "Set Music Loop Configuration.md",
            "title": "Set Music Loop Configuration.md",
            "depth": 4,
            "order": 22,
            "is_dir": false,
            "icon": "",
            "status": 1,
            "filepath": "Ue/blueprint/zh/Meta Sound Parameter Pack/Set Music Loop Configuration.md",
            "url": "Ue/blueprint/zh/MetaSoundParameterPack/SetMusicLoopConfiguration.md"
        },
        {
            "name": "Set Music Seek Request.md",
            "title": "Set Music Seek Request.md",
            "depth": 4,
            "order": 23,
            "is_dir": false,
            "icon": "",
            "status": 1,
            "filepath": "Ue/blueprint/zh/Meta Sound Parameter Pack/Set Music Seek Request.md",
            "url": "Ue/blueprint/zh/MetaSoundParameterPack/SetMusicSeekRequest.md"
        },
        {
            "name": "Set Music Timestamp.md",
            "title": "Set Music Timestamp.md",
            "depth": 4,
            "order": 24,
            "is_dir": false,
            "icon": "",
            "status": 1,
            "filepath": "Ue/blueprint/zh/Meta Sound Parameter Pack/Set Music Timestamp.md",
            "url": "Ue/blueprint/zh/MetaSoundParameterPack/SetMusicTimestamp.md"
        },
        {
            "name": "Set String.md",
            "title": "Set String.md",
            "depth": 4,
            "order": 25,
            "is_dir": false,
            "icon": "",
            "status": 1,
            "filepath": "Ue/blueprint/zh/Meta Sound Parameter Pack/Set String.md",
            "url": "Ue/blueprint/zh/MetaSoundParameterPack/SetString.md"
        },
        {
            "name": "Set Trigger.md",
            "title": "Set Trigger.md",
            "depth": 4,
            "order": 26,
            "is_dir": false,
            "icon": "",
            "status": 1,
            "filepath": "Ue/blueprint/zh/Meta Sound Parameter Pack/Set Trigger.md",
            "url": "Ue/blueprint/zh/MetaSoundParameterPack/SetTrigger.md"
        }
    ],
    "categorys": []
}