{
    "documents": [
        {
            "name": "Auto Generate Patch Builder Mesh UVs.md",
            "title": "Auto Generate Patch Builder Mesh UVs.md",
            "depth": 5,
            "order": 1,
            "is_dir": false,
            "icon": "",
            "status": 1,
            "filepath": "Ue/blueprint/zh/Geometry Script/UVs/Auto Generate Patch Builder Mesh UVs.md",
            "url": "Ue/blueprint/zh/GeometryScript/UVs/AutoGeneratePatchBuilderMeshUVs.md"
        },
        {
            "name": "Auto Generate XAtlas Mesh UVs.md",
            "title": "Auto Generate XAtlas Mesh UVs.md",
            "depth": 5,
            "order": 2,
            "is_dir": false,
            "icon": "",
            "status": 1,
            "filepath": "Ue/blueprint/zh/Geometry Script/UVs/Auto Generate XAtlas Mesh UVs.md",
            "url": "Ue/blueprint/zh/GeometryScript/UVs/AutoGenerateXAtlasMeshUVs.md"
        },
        {
            "name": "Compute Mesh Local UVParam.md",
            "title": "Compute Mesh Local UVParam.md",
            "depth": 5,
            "order": 3,
            "is_dir": false,
            "icon": "",
            "status": 1,
            "filepath": "Ue/blueprint/zh/Geometry Script/UVs/Compute Mesh Local UVParam.md",
            "url": "Ue/blueprint/zh/GeometryScript/UVs/ComputeMeshLocalUVParam.md"
        },
        {
            "name": "Copy Mesh To Mesh UV Channel.md",
            "title": "Copy Mesh To Mesh UV Channel.md",
            "depth": 5,
            "order": 4,
            "is_dir": false,
            "icon": "",
            "status": 1,
            "filepath": "Ue/blueprint/zh/Geometry Script/UVs/Copy Mesh To Mesh UV Channel.md",
            "url": "Ue/blueprint/zh/GeometryScript/UVs/CopyMeshToMeshUVChannel.md"
        },
        {
            "name": "Copy Mesh UV Channel To Mesh.md",
            "title": "Copy Mesh UV Channel To Mesh.md",
            "depth": 5,
            "order": 5,
            "is_dir": false,
            "icon": "",
            "status": 1,
            "filepath": "Ue/blueprint/zh/Geometry Script/UVs/Copy Mesh UV Channel To Mesh.md",
            "url": "Ue/blueprint/zh/GeometryScript/UVs/CopyMeshUVChannelToMesh.md"
        },
        {
            "name": "Copy UV Channel.md",
            "title": "Copy UV Channel.md",
            "depth": 5,
            "order": 6,
            "is_dir": false,
            "icon": "",
            "status": 1,
            "filepath": "Ue/blueprint/zh/Geometry Script/UVs/Copy UV Channel.md",
            "url": "Ue/blueprint/zh/GeometryScript/UVs/CopyUVChannel.md"
        },
        {
            "name": "Get Mesh Per Vertex UVs.md",
            "title": "Get Mesh Per Vertex UVs.md",
            "depth": 5,
            "order": 7,
            "is_dir": false,
            "icon": "",
            "status": 1,
            "filepath": "Ue/blueprint/zh/Geometry Script/UVs/Get Mesh Per Vertex UVs.md",
            "url": "Ue/blueprint/zh/GeometryScript/UVs/GetMeshPerVertexUVs.md"
        },
        {
            "name": "Get Mesh Triangle UVElement IDs.md",
            "title": "Get Mesh Triangle UVElement IDs.md",
            "depth": 5,
            "order": 8,
            "is_dir": false,
            "icon": "",
            "status": 1,
            "filepath": "Ue/blueprint/zh/Geometry Script/UVs/Get Mesh Triangle UVElement IDs.md",
            "url": "Ue/blueprint/zh/GeometryScript/UVs/GetMeshTriangleUVElementIDs.md"
        },
        {
            "name": "Get Mesh UVElement Position.md",
            "title": "Get Mesh UVElement Position.md",
            "depth": 5,
            "order": 9,
            "is_dir": false,
            "icon": "",
            "status": 1,
            "filepath": "Ue/blueprint/zh/Geometry Script/UVs/Get Mesh UVElement Position.md",
            "url": "Ue/blueprint/zh/GeometryScript/UVs/GetMeshUVElementPosition.md"
        },
        {
            "name": "Get Mesh UVSize Info.md",
            "title": "Get Mesh UVSize Info.md",
            "depth": 5,
            "order": 10,
            "is_dir": false,
            "icon": "",
            "status": 1,
            "filepath": "Ue/blueprint/zh/Geometry Script/UVs/Get Mesh UVSize Info.md",
            "url": "Ue/blueprint/zh/GeometryScript/UVs/GetMeshUVSizeInfo.md"
        },
        {
            "name": "Recompute Mesh UVs.md",
            "title": "Recompute Mesh UVs.md",
            "depth": 5,
            "order": 11,
            "is_dir": false,
            "icon": "",
            "status": 1,
            "filepath": "Ue/blueprint/zh/Geometry Script/UVs/Recompute Mesh UVs.md",
            "url": "Ue/blueprint/zh/GeometryScript/UVs/RecomputeMeshUVs.md"
        },
        {
            "name": "Repack Mesh UVs.md",
            "title": "Repack Mesh UVs.md",
            "depth": 5,
            "order": 12,
            "is_dir": false,
            "icon": "",
            "status": 1,
            "filepath": "Ue/blueprint/zh/Geometry Script/UVs/Repack Mesh UVs.md",
            "url": "Ue/blueprint/zh/GeometryScript/UVs/RepackMeshUVs.md"
        },
        {
            "name": "Rotate Mesh UVs.md",
            "title": "Rotate Mesh UVs.md",
            "depth": 5,
            "order": 13,
            "is_dir": false,
            "icon": "",
            "status": 1,
            "filepath": "Ue/blueprint/zh/Geometry Script/UVs/Rotate Mesh UVs.md",
            "url": "Ue/blueprint/zh/GeometryScript/UVs/RotateMeshUVs.md"
        },
        {
            "name": "Scale Mesh UVs.md",
            "title": "Scale Mesh UVs.md",
            "depth": 5,
            "order": 14,
            "is_dir": false,
            "icon": "",
            "status": 1,
            "filepath": "Ue/blueprint/zh/Geometry Script/UVs/Scale Mesh UVs.md",
            "url": "Ue/blueprint/zh/GeometryScript/UVs/ScaleMeshUVs.md"
        },
        {
            "name": "Set Mesh Triangle UVElement IDs.md",
            "title": "Set Mesh Triangle UVElement IDs.md",
            "depth": 5,
            "order": 15,
            "is_dir": false,
            "icon": "",
            "status": 1,
            "filepath": "Ue/blueprint/zh/Geometry Script/UVs/Set Mesh Triangle UVElement IDs.md",
            "url": "Ue/blueprint/zh/GeometryScript/UVs/SetMeshTriangleUVElementIDs.md"
        },
        {
            "name": "Set Mesh Triangle UVs.md",
            "title": "Set Mesh Triangle UVs.md",
            "depth": 5,
            "order": 16,
            "is_dir": false,
            "icon": "",
            "status": 1,
            "filepath": "Ue/blueprint/zh/Geometry Script/UVs/Set Mesh Triangle UVs.md",
            "url": "Ue/blueprint/zh/GeometryScript/UVs/SetMeshTriangleUVs.md"
        },
        {
            "name": "Set Mesh UVElement Position.md",
            "title": "Set Mesh UVElement Position.md",
            "depth": 5,
            "order": 17,
            "is_dir": false,
            "icon": "",
            "status": 1,
            "filepath": "Ue/blueprint/zh/Geometry Script/UVs/Set Mesh UVElement Position.md",
            "url": "Ue/blueprint/zh/GeometryScript/UVs/SetMeshUVElementPosition.md"
        },
        {
            "name": "Set Mesh UVs from Box Projection.md",
            "title": "Set Mesh UVs from Box Projection.md",
            "depth": 5,
            "order": 18,
            "is_dir": false,
            "icon": "",
            "status": 1,
            "filepath": "Ue/blueprint/zh/Geometry Script/UVs/Set Mesh UVs from Box Projection.md",
            "url": "Ue/blueprint/zh/GeometryScript/UVs/SetMeshUVsfromBoxProjection.md"
        },
        {
            "name": "Set Mesh UVs from Cylinder Projection.md",
            "title": "Set Mesh UVs from Cylinder Projection.md",
            "depth": 5,
            "order": 19,
            "is_dir": false,
            "icon": "",
            "status": 1,
            "filepath": "Ue/blueprint/zh/Geometry Script/UVs/Set Mesh UVs from Cylinder Projection.md",
            "url": "Ue/blueprint/zh/GeometryScript/UVs/SetMeshUVsfromCylinderProjection.md"
        },
        {
            "name": "Set Mesh UVs from Planar Projection.md",
            "title": "Set Mesh UVs from Planar Projection.md",
            "depth": 5,
            "order": 20,
            "is_dir": false,
            "icon": "",
            "status": 1,
            "filepath": "Ue/blueprint/zh/Geometry Script/UVs/Set Mesh UVs from Planar Projection.md",
            "url": "Ue/blueprint/zh/GeometryScript/UVs/SetMeshUVsfromPlanarProjection.md"
        },
        {
            "name": "Set Num UV Channels.md",
            "title": "Set Num UV Channels.md",
            "depth": 5,
            "order": 21,
            "is_dir": false,
            "icon": "",
            "status": 1,
            "filepath": "Ue/blueprint/zh/Geometry Script/UVs/Set Num UV Channels.md",
            "url": "Ue/blueprint/zh/GeometryScript/UVs/SetNumUVChannels.md"
        },
        {
            "name": "Translate Mesh UVs.md",
            "title": "Translate Mesh UVs.md",
            "depth": 5,
            "order": 22,
            "is_dir": false,
            "icon": "",
            "status": 1,
            "filepath": "Ue/blueprint/zh/Geometry Script/UVs/Translate Mesh UVs.md",
            "url": "Ue/blueprint/zh/GeometryScript/UVs/TranslateMeshUVs.md"
        }
    ],
    "categorys": []
}