{
    "documents": [
        {
            "name": "Is Listening to Player.md",
            "title": "Is Listening to Player.md",
            "depth": 4,
            "order": 1,
            "is_dir": false,
            "icon": "",
            "status": 1,
            "filepath": "Ue/blueprint/zh/Pixel Streaming Audio Component/Is Listening to Player.md",
            "url": "Ue/blueprint/zh/PixelStreamingAudioComponent/IsListeningtoPlayer.md"
        },
        {
            "name": "Listen To.md",
            "title": "Listen To.md",
            "depth": 4,
            "order": 2,
            "is_dir": false,
            "icon": "",
            "status": 1,
            "filepath": "Ue/blueprint/zh/Pixel Streaming Audio Component/Listen To.md",
            "url": "Ue/blueprint/zh/PixelStreamingAudioComponent/ListenTo.md"
        },
        {
            "name": "Reset.md",
            "title": "Reset.md",
            "depth": 4,
            "order": 3,
            "is_dir": false,
            "icon": "",
            "status": 1,
            "filepath": "Ue/blueprint/zh/Pixel Streaming Audio Component/Reset.md",
            "url": "Ue/blueprint/zh/PixelStreamingAudioComponent/Reset.md"
        },
        {
            "name": "Streamer Listen To.md",
            "title": "Streamer Listen To.md",
            "depth": 4,
            "order": 4,
            "is_dir": false,
            "icon": "",
            "status": 1,
            "filepath": "Ue/blueprint/zh/Pixel Streaming Audio Component/Streamer Listen To.md",
            "url": "Ue/blueprint/zh/PixelStreamingAudioComponent/StreamerListenTo.md"
        }
    ],
    "categorys": []
}