{
    "documents": [
        {
            "name": "Get Render Transform Angle.md",
            "title": "Get Render Transform Angle.md",
            "depth": 5,
            "order": 1,
            "is_dir": false,
            "icon": "",
            "status": 1,
            "filepath": "Ue/blueprint/zh/Widget/Transform/Get Render Transform Angle.md",
            "url": "Ue/blueprint/zh/Widget/Transform/GetRenderTransformAngle.md"
        },
        {
            "name": "Set Render Scale.md",
            "title": "Set Render Scale.md",
            "depth": 5,
            "order": 2,
            "is_dir": false,
            "icon": "",
            "status": 1,
            "filepath": "Ue/blueprint/zh/Widget/Transform/Set Render Scale.md",
            "url": "Ue/blueprint/zh/Widget/Transform/SetRenderScale.md"
        },
        {
            "name": "Set Render Shear.md",
            "title": "Set Render Shear.md",
            "depth": 5,
            "order": 3,
            "is_dir": false,
            "icon": "",
            "status": 1,
            "filepath": "Ue/blueprint/zh/Widget/Transform/Set Render Shear.md",
            "url": "Ue/blueprint/zh/Widget/Transform/SetRenderShear.md"
        },
        {
            "name": "Set Render Transform Angle.md",
            "title": "Set Render Transform Angle.md",
            "depth": 5,
            "order": 4,
            "is_dir": false,
            "icon": "",
            "status": 1,
            "filepath": "Ue/blueprint/zh/Widget/Transform/Set Render Transform Angle.md",
            "url": "Ue/blueprint/zh/Widget/Transform/SetRenderTransformAngle.md"
        },
        {
            "name": "Set Render Transform Pivot.md",
            "title": "Set Render Transform Pivot.md",
            "depth": 5,
            "order": 5,
            "is_dir": false,
            "icon": "",
            "status": 1,
            "filepath": "Ue/blueprint/zh/Widget/Transform/Set Render Transform Pivot.md",
            "url": "Ue/blueprint/zh/Widget/Transform/SetRenderTransformPivot.md"
        },
        {
            "name": "Set Render Transform.md",
            "title": "Set Render Transform.md",
            "depth": 5,
            "order": 6,
            "is_dir": false,
            "icon": "",
            "status": 1,
            "filepath": "Ue/blueprint/zh/Widget/Transform/Set Render Transform.md",
            "url": "Ue/blueprint/zh/Widget/Transform/SetRenderTransform.md"
        },
        {
            "name": "Set Render Translation.md",
            "title": "Set Render Translation.md",
            "depth": 5,
            "order": 7,
            "is_dir": false,
            "icon": "",
            "status": 1,
            "filepath": "Ue/blueprint/zh/Widget/Transform/Set Render Translation.md",
            "url": "Ue/blueprint/zh/Widget/Transform/SetRenderTranslation.md"
        }
    ],
    "categorys": []
}