{
    "documents": [
        {
            "name": "Break Vector Net Quantize 10.md",
            "title": "Break Vector Net Quantize 10.md",
            "depth": 5,
            "order": 1,
            "is_dir": false,
            "icon": "",
            "status": 1,
            "filepath": "Ue/blueprint/en/Math/Vector/Break Vector Net Quantize 10.md",
            "url": "Ue/blueprint/en/Math/Vector/BreakVectorNetQuantize10.md"
        },
        {
            "name": "Break Vector Net Quantize 100.md",
            "title": "Break Vector Net Quantize 100.md",
            "depth": 5,
            "order": 2,
            "is_dir": false,
            "icon": "",
            "status": 1,
            "filepath": "Ue/blueprint/en/Math/Vector/Break Vector Net Quantize 100.md",
            "url": "Ue/blueprint/en/Math/Vector/BreakVectorNetQuantize100.md"
        },
        {
            "name": "Break Vector Net Quantize Normal.md",
            "title": "Break Vector Net Quantize Normal.md",
            "depth": 5,
            "order": 3,
            "is_dir": false,
            "icon": "",
            "status": 1,
            "filepath": "Ue/blueprint/en/Math/Vector/Break Vector Net Quantize Normal.md",
            "url": "Ue/blueprint/en/Math/Vector/BreakVectorNetQuantizeNormal.md"
        },
        {
            "name": "Break Vector Net Quantize.md",
            "title": "Break Vector Net Quantize.md",
            "depth": 5,
            "order": 4,
            "is_dir": false,
            "icon": "",
            "status": 1,
            "filepath": "Ue/blueprint/en/Math/Vector/Break Vector Net Quantize.md",
            "url": "Ue/blueprint/en/Math/Vector/BreakVectorNetQuantize.md"
        },
        {
            "name": "Break Vector.md",
            "title": "Break Vector.md",
            "depth": 5,
            "order": 5,
            "is_dir": false,
            "icon": "",
            "status": 1,
            "filepath": "Ue/blueprint/en/Math/Vector/Break Vector.md",
            "url": "Ue/blueprint/en/Math/Vector/BreakVector.md"
        },
        {
            "name": "Clamp Vector Size.md",
            "title": "Clamp Vector Size.md",
            "depth": 5,
            "order": 6,
            "is_dir": false,
            "icon": "",
            "status": 1,
            "filepath": "Ue/blueprint/en/Math/Vector/Clamp Vector Size.md",
            "url": "Ue/blueprint/en/Math/Vector/ClampVectorSize.md"
        },
        {
            "name": "Create Vector from Yaw Pitch.md",
            "title": "Create Vector from Yaw Pitch.md",
            "depth": 5,
            "order": 7,
            "is_dir": false,
            "icon": "",
            "status": 1,
            "filepath": "Ue/blueprint/en/Math/Vector/Create Vector from Yaw Pitch.md",
            "url": "Ue/blueprint/en/Math/Vector/CreateVectorfromYawPitch.md"
        },
        {
            "name": "Cross Product.md",
            "title": "Cross Product.md",
            "depth": 5,
            "order": 8,
            "is_dir": false,
            "icon": "",
            "status": 1,
            "filepath": "Ue/blueprint/en/Math/Vector/Cross Product.md",
            "url": "Ue/blueprint/en/Math/Vector/CrossProduct.md"
        },
        {
            "name": "Distance (Vector).md",
            "title": "Distance (Vector).md",
            "depth": 5,
            "order": 9,
            "is_dir": false,
            "icon": "",
            "status": 1,
            "filepath": "Ue/blueprint/en/Math/Vector/Distance (Vector).md",
            "url": "Ue/blueprint/en/Math/Vector/DistanceVector.md"
        },
        {
            "name": "Distance Squared (Vector).md",
            "title": "Distance Squared (Vector).md",
            "depth": 5,
            "order": 10,
            "is_dir": false,
            "icon": "",
            "status": 1,
            "filepath": "Ue/blueprint/en/Math/Vector/Distance Squared (Vector).md",
            "url": "Ue/blueprint/en/Math/Vector/DistanceSquaredVector.md"
        },
        {
            "name": "Distance2D (Vector).md",
            "title": "Distance2D (Vector).md",
            "depth": 5,
            "order": 11,
            "is_dir": false,
            "icon": "",
            "status": 1,
            "filepath": "Ue/blueprint/en/Math/Vector/Distance2D (Vector).md",
            "url": "Ue/blueprint/en/Math/Vector/Distance2DVector.md"
        },
        {
            "name": "Distance2D Squared (Vector).md",
            "title": "Distance2D Squared (Vector).md",
            "depth": 5,
            "order": 12,
            "is_dir": false,
            "icon": "",
            "status": 1,
            "filepath": "Ue/blueprint/en/Math/Vector/Distance2D Squared (Vector).md",
            "url": "Ue/blueprint/en/Math/Vector/Distance2DSquaredVector.md"
        },
        {
            "name": "Dot Product.md",
            "title": "Dot Product.md",
            "depth": 5,
            "order": 13,
            "is_dir": false,
            "icon": "",
            "status": 1,
            "filepath": "Ue/blueprint/en/Math/Vector/Dot Product.md",
            "url": "Ue/blueprint/en/Math/Vector/DotProduct.md"
        },
        {
            "name": "Equal Exactly (Vector).md",
            "title": "Equal Exactly (Vector).md",
            "depth": 5,
            "order": 14,
            "is_dir": false,
            "icon": "",
            "status": 1,
            "filepath": "Ue/blueprint/en/Math/Vector/Equal Exactly (Vector).md",
            "url": "Ue/blueprint/en/Math/Vector/EqualExactlyVector.md"
        },
        {
            "name": "Find Closest Point on Line.md",
            "title": "Find Closest Point on Line.md",
            "depth": 5,
            "order": 15,
            "is_dir": false,
            "icon": "",
            "status": 1,
            "filepath": "Ue/blueprint/en/Math/Vector/Find Closest Point on Line.md",
            "url": "Ue/blueprint/en/Math/Vector/FindClosestPointonLine.md"
        },
        {
            "name": "Find Closest Point on Segment.md",
            "title": "Find Closest Point on Segment.md",
            "depth": 5,
            "order": 16,
            "is_dir": false,
            "icon": "",
            "status": 1,
            "filepath": "Ue/blueprint/en/Math/Vector/Find Closest Point on Segment.md",
            "url": "Ue/blueprint/en/Math/Vector/FindClosestPointonSegment.md"
        },
        {
            "name": "Find Nearest Points on Line Segments.md",
            "title": "Find Nearest Points on Line Segments.md",
            "depth": 5,
            "order": 17,
            "is_dir": false,
            "icon": "",
            "status": 1,
            "filepath": "Ue/blueprint/en/Math/Vector/Find Nearest Points on Line Segments.md",
            "url": "Ue/blueprint/en/Math/Vector/FindNearestPointsonLineSegments.md"
        },
        {
            "name": "Get Azimuth and Elevation.md",
            "title": "Get Azimuth and Elevation.md",
            "depth": 5,
            "order": 18,
            "is_dir": false,
            "icon": "",
            "status": 1,
            "filepath": "Ue/blueprint/en/Math/Vector/Get Azimuth and Elevation.md",
            "url": "Ue/blueprint/en/Math/Vector/GetAzimuthandElevation.md"
        },
        {
            "name": "Get Forward Vector.md",
            "title": "Get Forward Vector.md",
            "depth": 5,
            "order": 19,
            "is_dir": false,
            "icon": "",
            "status": 1,
            "filepath": "Ue/blueprint/en/Math/Vector/Get Forward Vector.md",
            "url": "Ue/blueprint/en/Math/Vector/GetForwardVector.md"
        },
        {
            "name": "Get Max Element.md",
            "title": "Get Max Element.md",
            "depth": 5,
            "order": 20,
            "is_dir": false,
            "icon": "",
            "status": 1,
            "filepath": "Ue/blueprint/en/Math/Vector/Get Max Element.md",
            "url": "Ue/blueprint/en/Math/Vector/GetMaxElement.md"
        },
        {
            "name": "Get Min Element.md",
            "title": "Get Min Element.md",
            "depth": 5,
            "order": 21,
            "is_dir": false,
            "icon": "",
            "status": 1,
            "filepath": "Ue/blueprint/en/Math/Vector/Get Min Element.md",
            "url": "Ue/blueprint/en/Math/Vector/GetMinElement.md"
        },
        {
            "name": "Get Point Distance to Line.md",
            "title": "Get Point Distance to Line.md",
            "depth": 5,
            "order": 22,
            "is_dir": false,
            "icon": "",
            "status": 1,
            "filepath": "Ue/blueprint/en/Math/Vector/Get Point Distance to Line.md",
            "url": "Ue/blueprint/en/Math/Vector/GetPointDistancetoLine.md"
        },
        {
            "name": "Get Point Distance to Segment.md",
            "title": "Get Point Distance to Segment.md",
            "depth": 5,
            "order": 23,
            "is_dir": false,
            "icon": "",
            "status": 1,
            "filepath": "Ue/blueprint/en/Math/Vector/Get Point Distance to Segment.md",
            "url": "Ue/blueprint/en/Math/Vector/GetPointDistancetoSegment.md"
        },
        {
            "name": "Get Reflection Vector.md",
            "title": "Get Reflection Vector.md",
            "depth": 5,
            "order": 24,
            "is_dir": false,
            "icon": "",
            "status": 1,
            "filepath": "Ue/blueprint/en/Math/Vector/Get Reflection Vector.md",
            "url": "Ue/blueprint/en/Math/Vector/GetReflectionVector.md"
        },
        {
            "name": "Get Right Vector.md",
            "title": "Get Right Vector.md",
            "depth": 5,
            "order": 25,
            "is_dir": false,
            "icon": "",
            "status": 1,
            "filepath": "Ue/blueprint/en/Math/Vector/Get Right Vector.md",
            "url": "Ue/blueprint/en/Math/Vector/GetRightVector.md"
        },
        {
            "name": "Get Unit Direction (Vector).md",
            "title": "Get Unit Direction (Vector).md",
            "depth": 5,
            "order": 26,
            "is_dir": false,
            "icon": "",
            "status": 1,
            "filepath": "Ue/blueprint/en/Math/Vector/Get Unit Direction (Vector).md",
            "url": "Ue/blueprint/en/Math/Vector/GetUnitDirectionVector.md"
        },
        {
            "name": "Get Up Vector.md",
            "title": "Get Up Vector.md",
            "depth": 5,
            "order": 27,
            "is_dir": false,
            "icon": "",
            "status": 1,
            "filepath": "Ue/blueprint/en/Math/Vector/Get Up Vector.md",
            "url": "Ue/blueprint/en/Math/Vector/GetUpVector.md"
        },
        {
            "name": "Get Vector Array Average.md",
            "title": "Get Vector Array Average.md",
            "depth": 5,
            "order": 28,
            "is_dir": false,
            "icon": "",
            "status": 1,
            "filepath": "Ue/blueprint/en/Math/Vector/Get Vector Array Average.md",
            "url": "Ue/blueprint/en/Math/Vector/GetVectorArrayAverage.md"
        },
        {
            "name": "Get Yaw Pitch from Vector.md",
            "title": "Get Yaw Pitch from Vector.md",
            "depth": 5,
            "order": 29,
            "is_dir": false,
            "icon": "",
            "status": 1,
            "filepath": "Ue/blueprint/en/Math/Vector/Get Yaw Pitch from Vector.md",
            "url": "Ue/blueprint/en/Math/Vector/GetYawPitchfromVector.md"
        },
        {
            "name": "Is Normal (Vector).md",
            "title": "Is Normal (Vector).md",
            "depth": 5,
            "order": 30,
            "is_dir": false,
            "icon": "",
            "status": 1,
            "filepath": "Ue/blueprint/en/Math/Vector/Is Normal (Vector).md",
            "url": "Ue/blueprint/en/Math/Vector/IsNormalVector.md"
        },
        {
            "name": "Is Uniform (Vector).md",
            "title": "Is Uniform (Vector).md",
            "depth": 5,
            "order": 31,
            "is_dir": false,
            "icon": "",
            "status": 1,
            "filepath": "Ue/blueprint/en/Math/Vector/Is Uniform (Vector).md",
            "url": "Ue/blueprint/en/Math/Vector/IsUniformVector.md"
        },
        {
            "name": "Is Unit (Vector).md",
            "title": "Is Unit (Vector).md",
            "depth": 5,
            "order": 32,
            "is_dir": false,
            "icon": "",
            "status": 1,
            "filepath": "Ue/blueprint/en/Math/Vector/Is Unit (Vector).md",
            "url": "Ue/blueprint/en/Math/Vector/IsUnitVector.md"
        },
        {
            "name": "Lerp (Vector).md",
            "title": "Lerp (Vector).md",
            "depth": 5,
            "order": 33,
            "is_dir": false,
            "icon": "",
            "status": 1,
            "filepath": "Ue/blueprint/en/Math/Vector/Lerp (Vector).md",
            "url": "Ue/blueprint/en/Math/Vector/LerpVector.md"
        },
        {
            "name": "Make Vector Net Quantize 10.md",
            "title": "Make Vector Net Quantize 10.md",
            "depth": 5,
            "order": 34,
            "is_dir": false,
            "icon": "",
            "status": 1,
            "filepath": "Ue/blueprint/en/Math/Vector/Make Vector Net Quantize 10.md",
            "url": "Ue/blueprint/en/Math/Vector/MakeVectorNetQuantize10.md"
        },
        {
            "name": "Make Vector Net Quantize 100.md",
            "title": "Make Vector Net Quantize 100.md",
            "depth": 5,
            "order": 35,
            "is_dir": false,
            "icon": "",
            "status": 1,
            "filepath": "Ue/blueprint/en/Math/Vector/Make Vector Net Quantize 100.md",
            "url": "Ue/blueprint/en/Math/Vector/MakeVectorNetQuantize100.md"
        },
        {
            "name": "Make Vector Net Quantize Normal.md",
            "title": "Make Vector Net Quantize Normal.md",
            "depth": 5,
            "order": 36,
            "is_dir": false,
            "icon": "",
            "status": 1,
            "filepath": "Ue/blueprint/en/Math/Vector/Make Vector Net Quantize Normal.md",
            "url": "Ue/blueprint/en/Math/Vector/MakeVectorNetQuantizeNormal.md"
        },
        {
            "name": "Make Vector Net Quantize.md",
            "title": "Make Vector Net Quantize.md",
            "depth": 5,
            "order": 37,
            "is_dir": false,
            "icon": "",
            "status": 1,
            "filepath": "Ue/blueprint/en/Math/Vector/Make Vector Net Quantize.md",
            "url": "Ue/blueprint/en/Math/Vector/MakeVectorNetQuantize.md"
        },
        {
            "name": "Make Vector.md",
            "title": "Make Vector.md",
            "depth": 5,
            "order": 38,
            "is_dir": false,
            "icon": "",
            "status": 1,
            "filepath": "Ue/blueprint/en/Math/Vector/Make Vector.md",
            "url": "Ue/blueprint/en/Math/Vector/MakeVector.md"
        },
        {
            "name": "Mirror Vector by Normal.md",
            "title": "Mirror Vector by Normal.md",
            "depth": 5,
            "order": 39,
            "is_dir": false,
            "icon": "",
            "status": 1,
            "filepath": "Ue/blueprint/en/Math/Vector/Mirror Vector by Normal.md",
            "url": "Ue/blueprint/en/Math/Vector/MirrorVectorbyNormal.md"
        },
        {
            "name": "Negate Vector.md",
            "title": "Negate Vector.md",
            "depth": 5,
            "order": 40,
            "is_dir": false,
            "icon": "",
            "status": 1,
            "filepath": "Ue/blueprint/en/Math/Vector/Negate Vector.md",
            "url": "Ue/blueprint/en/Math/Vector/NegateVector.md"
        },
        {
            "name": "Normal Unsafe (Vector).md",
            "title": "Normal Unsafe (Vector).md",
            "depth": 5,
            "order": 41,
            "is_dir": false,
            "icon": "",
            "status": 1,
            "filepath": "Ue/blueprint/en/Math/Vector/Normal Unsafe (Vector).md",
            "url": "Ue/blueprint/en/Math/Vector/NormalUnsafeVector.md"
        },
        {
            "name": "Normalize 2D (Vector).md",
            "title": "Normalize 2D (Vector).md",
            "depth": 5,
            "order": 42,
            "is_dir": false,
            "icon": "",
            "status": 1,
            "filepath": "Ue/blueprint/en/Math/Vector/Normalize 2D (Vector).md",
            "url": "Ue/blueprint/en/Math/Vector/Normalize2DVector.md"
        },
        {
            "name": "Normalize In Place (Vector).md",
            "title": "Normalize In Place (Vector).md",
            "depth": 5,
            "order": 43,
            "is_dir": false,
            "icon": "",
            "status": 1,
            "filepath": "Ue/blueprint/en/Math/Vector/Normalize In Place (Vector).md",
            "url": "Ue/blueprint/en/Math/Vector/NormalizeInPlaceVector.md"
        },
        {
            "name": "Normalize.md",
            "title": "Normalize.md",
            "depth": 5,
            "order": 44,
            "is_dir": false,
            "icon": "",
            "status": 1,
            "filepath": "Ue/blueprint/en/Math/Vector/Normalize.md",
            "url": "Ue/blueprint/en/Math/Vector/Normalize.md"
        },
        {
            "name": "Not Equal Exactly (Vector).md",
            "title": "Not Equal Exactly (Vector).md",
            "depth": 5,
            "order": 45,
            "is_dir": false,
            "icon": "",
            "status": 1,
            "filepath": "Ue/blueprint/en/Math/Vector/Not Equal Exactly (Vector).md",
            "url": "Ue/blueprint/en/Math/Vector/NotEqualExactlyVector.md"
        },
        {
            "name": "Project Point on to Plane.md",
            "title": "Project Point on to Plane.md",
            "depth": 5,
            "order": 46,
            "is_dir": false,
            "icon": "",
            "status": 1,
            "filepath": "Ue/blueprint/en/Math/Vector/Project Point on to Plane.md",
            "url": "Ue/blueprint/en/Math/Vector/ProjectPointontoPlane.md"
        },
        {
            "name": "Project Vector on to Plane.md",
            "title": "Project Vector on to Plane.md",
            "depth": 5,
            "order": 47,
            "is_dir": false,
            "icon": "",
            "status": 1,
            "filepath": "Ue/blueprint/en/Math/Vector/Project Vector on to Plane.md",
            "url": "Ue/blueprint/en/Math/Vector/ProjectVectorontoPlane.md"
        },
        {
            "name": "Project Vector on to Vector.md",
            "title": "Project Vector on to Vector.md",
            "depth": 5,
            "order": 48,
            "is_dir": false,
            "icon": "",
            "status": 1,
            "filepath": "Ue/blueprint/en/Math/Vector/Project Vector on to Vector.md",
            "url": "Ue/blueprint/en/Math/Vector/ProjectVectorontoVector.md"
        },
        {
            "name": "Reciprocal (Vector).md",
            "title": "Reciprocal (Vector).md",
            "depth": 5,
            "order": 49,
            "is_dir": false,
            "icon": "",
            "status": 1,
            "filepath": "Ue/blueprint/en/Math/Vector/Reciprocal (Vector).md",
            "url": "Ue/blueprint/en/Math/Vector/ReciprocalVector.md"
        },
        {
            "name": "Rotate Vector Around Axis.md",
            "title": "Rotate Vector Around Axis.md",
            "depth": 5,
            "order": 50,
            "is_dir": false,
            "icon": "",
            "status": 1,
            "filepath": "Ue/blueprint/en/Math/Vector/Rotate Vector Around Axis.md",
            "url": "Ue/blueprint/en/Math/Vector/RotateVectorAroundAxis.md"
        },
        {
            "name": "Rotate Vector.md",
            "title": "Rotate Vector.md",
            "depth": 5,
            "order": 51,
            "is_dir": false,
            "icon": "",
            "status": 1,
            "filepath": "Ue/blueprint/en/Math/Vector/Rotate Vector.md",
            "url": "Ue/blueprint/en/Math/Vector/RotateVector.md"
        },
        {
            "name": "Rotator from Axis and Angle.md",
            "title": "Rotator from Axis and Angle.md",
            "depth": 5,
            "order": 52,
            "is_dir": false,
            "icon": "",
            "status": 1,
            "filepath": "Ue/blueprint/en/Math/Vector/Rotator from Axis and Angle.md",
            "url": "Ue/blueprint/en/Math/Vector/RotatorfromAxisandAngle.md"
        },
        {
            "name": "Select Vector.md",
            "title": "Select Vector.md",
            "depth": 5,
            "order": 53,
            "is_dir": false,
            "icon": "",
            "status": 1,
            "filepath": "Ue/blueprint/en/Math/Vector/Select Vector.md",
            "url": "Ue/blueprint/en/Math/Vector/SelectVector.md"
        },
        {
            "name": "SlerpNormals.md",
            "title": "SlerpNormals.md",
            "depth": 5,
            "order": 54,
            "is_dir": false,
            "icon": "",
            "status": 1,
            "filepath": "Ue/blueprint/en/Math/Vector/SlerpNormals.md",
            "url": "Ue/blueprint/en/Math/Vector/SlerpNormals.md"
        },
        {
            "name": "SlerpVectorToDirection.md",
            "title": "SlerpVectorToDirection.md",
            "depth": 5,
            "order": 55,
            "is_dir": false,
            "icon": "",
            "status": 1,
            "filepath": "Ue/blueprint/en/Math/Vector/SlerpVectorToDirection.md",
            "url": "Ue/blueprint/en/Math/Vector/SlerpVectorToDirection.md"
        },
        {
            "name": "Unrotate Vector.md",
            "title": "Unrotate Vector.md",
            "depth": 5,
            "order": 56,
            "is_dir": false,
            "icon": "",
            "status": 1,
            "filepath": "Ue/blueprint/en/Math/Vector/Unrotate Vector.md",
            "url": "Ue/blueprint/en/Math/Vector/UnrotateVector.md"
        },
        {
            "name": "Vector Add Bounded.md",
            "title": "Vector Add Bounded.md",
            "depth": 5,
            "order": 57,
            "is_dir": false,
            "icon": "",
            "status": 1,
            "filepath": "Ue/blueprint/en/Math/Vector/Vector Add Bounded.md",
            "url": "Ue/blueprint/en/Math/Vector/VectorAddBounded.md"
        },
        {
            "name": "Vector Assign.md",
            "title": "Vector Assign.md",
            "depth": 5,
            "order": 58,
            "is_dir": false,
            "icon": "",
            "status": 1,
            "filepath": "Ue/blueprint/en/Math/Vector/Vector Assign.md",
            "url": "Ue/blueprint/en/Math/Vector/VectorAssign.md"
        },
        {
            "name": "Vector Backward.md",
            "title": "Vector Backward.md",
            "depth": 5,
            "order": 59,
            "is_dir": false,
            "icon": "",
            "status": 1,
            "filepath": "Ue/blueprint/en/Math/Vector/Vector Backward.md",
            "url": "Ue/blueprint/en/Math/Vector/VectorBackward.md"
        },
        {
            "name": "Vector Bounded to Box.md",
            "title": "Vector Bounded to Box.md",
            "depth": 5,
            "order": 60,
            "is_dir": false,
            "icon": "",
            "status": 1,
            "filepath": "Ue/blueprint/en/Math/Vector/Vector Bounded to Box.md",
            "url": "Ue/blueprint/en/Math/Vector/VectorBoundedtoBox.md"
        },
        {
            "name": "Vector Bounded to Cube.md",
            "title": "Vector Bounded to Cube.md",
            "depth": 5,
            "order": 61,
            "is_dir": false,
            "icon": "",
            "status": 1,
            "filepath": "Ue/blueprint/en/Math/Vector/Vector Bounded to Cube.md",
            "url": "Ue/blueprint/en/Math/Vector/VectorBoundedtoCube.md"
        },
        {
            "name": "Vector Clamp Size 2D.md",
            "title": "Vector Clamp Size 2D.md",
            "depth": 5,
            "order": 62,
            "is_dir": false,
            "icon": "",
            "status": 1,
            "filepath": "Ue/blueprint/en/Math/Vector/Vector Clamp Size 2D.md",
            "url": "Ue/blueprint/en/Math/Vector/VectorClampSize2D.md"
        },
        {
            "name": "Vector Clamp Size Max 2D.md",
            "title": "Vector Clamp Size Max 2D.md",
            "depth": 5,
            "order": 63,
            "is_dir": false,
            "icon": "",
            "status": 1,
            "filepath": "Ue/blueprint/en/Math/Vector/Vector Clamp Size Max 2D.md",
            "url": "Ue/blueprint/en/Math/Vector/VectorClampSizeMax2D.md"
        },
        {
            "name": "Vector Clamp Size Max.md",
            "title": "Vector Clamp Size Max.md",
            "depth": 5,
            "order": 64,
            "is_dir": false,
            "icon": "",
            "status": 1,
            "filepath": "Ue/blueprint/en/Math/Vector/Vector Clamp Size Max.md",
            "url": "Ue/blueprint/en/Math/Vector/VectorClampSizeMax.md"
        },
        {
            "name": "Vector Component Max.md",
            "title": "Vector Component Max.md",
            "depth": 5,
            "order": 65,
            "is_dir": false,
            "icon": "",
            "status": 1,
            "filepath": "Ue/blueprint/en/Math/Vector/Vector Component Max.md",
            "url": "Ue/blueprint/en/Math/Vector/VectorComponentMax.md"
        },
        {
            "name": "Vector Component Min.md",
            "title": "Vector Component Min.md",
            "depth": 5,
            "order": 66,
            "is_dir": false,
            "icon": "",
            "status": 1,
            "filepath": "Ue/blueprint/en/Math/Vector/Vector Component Min.md",
            "url": "Ue/blueprint/en/Math/Vector/VectorComponentMin.md"
        },
        {
            "name": "Vector Cosine Angle 2D.md",
            "title": "Vector Cosine Angle 2D.md",
            "depth": 5,
            "order": 67,
            "is_dir": false,
            "icon": "",
            "status": 1,
            "filepath": "Ue/blueprint/en/Math/Vector/Vector Cosine Angle 2D.md",
            "url": "Ue/blueprint/en/Math/Vector/VectorCosineAngle2D.md"
        },
        {
            "name": "Vector Down.md",
            "title": "Vector Down.md",
            "depth": 5,
            "order": 68,
            "is_dir": false,
            "icon": "",
            "status": 1,
            "filepath": "Ue/blueprint/en/Math/Vector/Vector Down.md",
            "url": "Ue/blueprint/en/Math/Vector/VectorDown.md"
        },
        {
            "name": "Vector Forward.md",
            "title": "Vector Forward.md",
            "depth": 5,
            "order": 69,
            "is_dir": false,
            "icon": "",
            "status": 1,
            "filepath": "Ue/blueprint/en/Math/Vector/Vector Forward.md",
            "url": "Ue/blueprint/en/Math/Vector/VectorForward.md"
        },
        {
            "name": "Vector Get Abs Max.md",
            "title": "Vector Get Abs Max.md",
            "depth": 5,
            "order": 70,
            "is_dir": false,
            "icon": "",
            "status": 1,
            "filepath": "Ue/blueprint/en/Math/Vector/Vector Get Abs Max.md",
            "url": "Ue/blueprint/en/Math/Vector/VectorGetAbsMax.md"
        },
        {
            "name": "Vector Get Abs Min.md",
            "title": "Vector Get Abs Min.md",
            "depth": 5,
            "order": 71,
            "is_dir": false,
            "icon": "",
            "status": 1,
            "filepath": "Ue/blueprint/en/Math/Vector/Vector Get Abs Min.md",
            "url": "Ue/blueprint/en/Math/Vector/VectorGetAbsMin.md"
        },
        {
            "name": "Vector Get Abs.md",
            "title": "Vector Get Abs.md",
            "depth": 5,
            "order": 72,
            "is_dir": false,
            "icon": "",
            "status": 1,
            "filepath": "Ue/blueprint/en/Math/Vector/Vector Get Abs.md",
            "url": "Ue/blueprint/en/Math/Vector/VectorGetAbs.md"
        },
        {
            "name": "Vector Get Projection.md",
            "title": "Vector Get Projection.md",
            "depth": 5,
            "order": 73,
            "is_dir": false,
            "icon": "",
            "status": 1,
            "filepath": "Ue/blueprint/en/Math/Vector/Vector Get Projection.md",
            "url": "Ue/blueprint/en/Math/Vector/VectorGetProjection.md"
        },
        {
            "name": "Vector Get Sign Vector.md",
            "title": "Vector Get Sign Vector.md",
            "depth": 5,
            "order": 74,
            "is_dir": false,
            "icon": "",
            "status": 1,
            "filepath": "Ue/blueprint/en/Math/Vector/Vector Get Sign Vector.md",
            "url": "Ue/blueprint/en/Math/Vector/VectorGetSignVector.md"
        },
        {
            "name": "Vector Heading Angle.md",
            "title": "Vector Heading Angle.md",
            "depth": 5,
            "order": 75,
            "is_dir": false,
            "icon": "",
            "status": 1,
            "filepath": "Ue/blueprint/en/Math/Vector/Vector Heading Angle.md",
            "url": "Ue/blueprint/en/Math/Vector/VectorHeadingAngle.md"
        },
        {
            "name": "Vector Is NAN.md",
            "title": "Vector Is NAN.md",
            "depth": 5,
            "order": 76,
            "is_dir": false,
            "icon": "",
            "status": 1,
            "filepath": "Ue/blueprint/en/Math/Vector/Vector Is NAN.md",
            "url": "Ue/blueprint/en/Math/Vector/VectorIsNAN.md"
        },
        {
            "name": "Vector Is Nearly Zero.md",
            "title": "Vector Is Nearly Zero.md",
            "depth": 5,
            "order": 77,
            "is_dir": false,
            "icon": "",
            "status": 1,
            "filepath": "Ue/blueprint/en/Math/Vector/Vector Is Nearly Zero.md",
            "url": "Ue/blueprint/en/Math/Vector/VectorIsNearlyZero.md"
        },
        {
            "name": "Vector Is Zero.md",
            "title": "Vector Is Zero.md",
            "depth": 5,
            "order": 78,
            "is_dir": false,
            "icon": "",
            "status": 1,
            "filepath": "Ue/blueprint/en/Math/Vector/Vector Is Zero.md",
            "url": "Ue/blueprint/en/Math/Vector/VectorIsZero.md"
        },
        {
            "name": "Vector Left.md",
            "title": "Vector Left.md",
            "depth": 5,
            "order": 79,
            "is_dir": false,
            "icon": "",
            "status": 1,
            "filepath": "Ue/blueprint/en/Math/Vector/Vector Left.md",
            "url": "Ue/blueprint/en/Math/Vector/VectorLeft.md"
        },
        {
            "name": "Vector Length Squared.md",
            "title": "Vector Length Squared.md",
            "depth": 5,
            "order": 80,
            "is_dir": false,
            "icon": "",
            "status": 1,
            "filepath": "Ue/blueprint/en/Math/Vector/Vector Length Squared.md",
            "url": "Ue/blueprint/en/Math/Vector/VectorLengthSquared.md"
        },
        {
            "name": "Vector Length XY Squared.md",
            "title": "Vector Length XY Squared.md",
            "depth": 5,
            "order": 81,
            "is_dir": false,
            "icon": "",
            "status": 1,
            "filepath": "Ue/blueprint/en/Math/Vector/Vector Length XY Squared.md",
            "url": "Ue/blueprint/en/Math/Vector/VectorLengthXYSquared.md"
        },
        {
            "name": "Vector Length XY.md",
            "title": "Vector Length XY.md",
            "depth": 5,
            "order": 82,
            "is_dir": false,
            "icon": "",
            "status": 1,
            "filepath": "Ue/blueprint/en/Math/Vector/Vector Length XY.md",
            "url": "Ue/blueprint/en/Math/Vector/VectorLengthXY.md"
        },
        {
            "name": "Vector Length.md",
            "title": "Vector Length.md",
            "depth": 5,
            "order": 83,
            "is_dir": false,
            "icon": "",
            "status": 1,
            "filepath": "Ue/blueprint/en/Math/Vector/Vector Length.md",
            "url": "Ue/blueprint/en/Math/Vector/VectorLength.md"
        },
        {
            "name": "Vector Mirror by Plane.md",
            "title": "Vector Mirror by Plane.md",
            "depth": 5,
            "order": 84,
            "is_dir": false,
            "icon": "",
            "status": 1,
            "filepath": "Ue/blueprint/en/Math/Vector/Vector Mirror by Plane.md",
            "url": "Ue/blueprint/en/Math/Vector/VectorMirrorbyPlane.md"
        },
        {
            "name": "Vector One.md",
            "title": "Vector One.md",
            "depth": 5,
            "order": 85,
            "is_dir": false,
            "icon": "",
            "status": 1,
            "filepath": "Ue/blueprint/en/Math/Vector/Vector One.md",
            "url": "Ue/blueprint/en/Math/Vector/VectorOne.md"
        },
        {
            "name": "Vector Project on to Normal.md",
            "title": "Vector Project on to Normal.md",
            "depth": 5,
            "order": 86,
            "is_dir": false,
            "icon": "",
            "status": 1,
            "filepath": "Ue/blueprint/en/Math/Vector/Vector Project on to Normal.md",
            "url": "Ue/blueprint/en/Math/Vector/VectorProjectontoNormal.md"
        },
        {
            "name": "Vector Right.md",
            "title": "Vector Right.md",
            "depth": 5,
            "order": 87,
            "is_dir": false,
            "icon": "",
            "status": 1,
            "filepath": "Ue/blueprint/en/Math/Vector/Vector Right.md",
            "url": "Ue/blueprint/en/Math/Vector/VectorRight.md"
        },
        {
            "name": "Vector Set.md",
            "title": "Vector Set.md",
            "depth": 5,
            "order": 88,
            "is_dir": false,
            "icon": "",
            "status": 1,
            "filepath": "Ue/blueprint/en/Math/Vector/Vector Set.md",
            "url": "Ue/blueprint/en/Math/Vector/VectorSet.md"
        },
        {
            "name": "Vector Snapped to Grid.md",
            "title": "Vector Snapped to Grid.md",
            "depth": 5,
            "order": 89,
            "is_dir": false,
            "icon": "",
            "status": 1,
            "filepath": "Ue/blueprint/en/Math/Vector/Vector Snapped to Grid.md",
            "url": "Ue/blueprint/en/Math/Vector/VectorSnappedtoGrid.md"
        },
        {
            "name": "Vector Unit Cartesian to Spherical.md",
            "title": "Vector Unit Cartesian to Spherical.md",
            "depth": 5,
            "order": 90,
            "is_dir": false,
            "icon": "",
            "status": 1,
            "filepath": "Ue/blueprint/en/Math/Vector/Vector Unit Cartesian to Spherical.md",
            "url": "Ue/blueprint/en/Math/Vector/VectorUnitCartesiantoSpherical.md"
        },
        {
            "name": "Vector Unwind Euler.md",
            "title": "Vector Unwind Euler.md",
            "depth": 5,
            "order": 91,
            "is_dir": false,
            "icon": "",
            "status": 1,
            "filepath": "Ue/blueprint/en/Math/Vector/Vector Unwind Euler.md",
            "url": "Ue/blueprint/en/Math/Vector/VectorUnwindEuler.md"
        },
        {
            "name": "Vector Up.md",
            "title": "Vector Up.md",
            "depth": 5,
            "order": 92,
            "is_dir": false,
            "icon": "",
            "status": 1,
            "filepath": "Ue/blueprint/en/Math/Vector/Vector Up.md",
            "url": "Ue/blueprint/en/Math/Vector/VectorUp.md"
        },
        {
            "name": "Vector Zero.md",
            "title": "Vector Zero.md",
            "depth": 5,
            "order": 93,
            "is_dir": false,
            "icon": "",
            "status": 1,
            "filepath": "Ue/blueprint/en/Math/Vector/Vector Zero.md",
            "url": "Ue/blueprint/en/Math/Vector/VectorZero.md"
        },
        {
            "name": "Vector to Degrees.md",
            "title": "Vector to Degrees.md",
            "depth": 5,
            "order": 94,
            "is_dir": false,
            "icon": "",
            "status": 1,
            "filepath": "Ue/blueprint/en/Math/Vector/Vector to Degrees.md",
            "url": "Ue/blueprint/en/Math/Vector/VectortoDegrees.md"
        },
        {
            "name": "Vector to Radians.md",
            "title": "Vector to Radians.md",
            "depth": 5,
            "order": 95,
            "is_dir": false,
            "icon": "",
            "status": 1,
            "filepath": "Ue/blueprint/en/Math/Vector/Vector to Radians.md",
            "url": "Ue/blueprint/en/Math/Vector/VectortoRadians.md"
        }
    ],
    "categorys": []
}