{
    "documents": [
        {
            "name": "Add Body Modifier to Set.md",
            "title": "Add Body Modifier to Set.md",
            "depth": 4,
            "order": 1,
            "is_dir": false,
            "icon": "",
            "status": 1,
            "filepath": "Ue/blueprint/zh/Physics Control/Add Body Modifier to Set.md",
            "url": "Ue/blueprint/zh/PhysicsControl/AddBodyModifiertoSet.md"
        },
        {
            "name": "Add Body Modifiers to Set.md",
            "title": "Add Body Modifiers to Set.md",
            "depth": 4,
            "order": 2,
            "is_dir": false,
            "icon": "",
            "status": 1,
            "filepath": "Ue/blueprint/zh/Physics Control/Add Body Modifiers to Set.md",
            "url": "Ue/blueprint/zh/PhysicsControl/AddBodyModifierstoSet.md"
        },
        {
            "name": "Add Control to Set.md",
            "title": "Add Control to Set.md",
            "depth": 4,
            "order": 3,
            "is_dir": false,
            "icon": "",
            "status": 1,
            "filepath": "Ue/blueprint/zh/Physics Control/Add Control to Set.md",
            "url": "Ue/blueprint/zh/PhysicsControl/AddControltoSet.md"
        },
        {
            "name": "Add Controls to Set.md",
            "title": "Add Controls to Set.md",
            "depth": 4,
            "order": 4,
            "is_dir": false,
            "icon": "",
            "status": 1,
            "filepath": "Ue/blueprint/zh/Physics Control/Add Controls to Set.md",
            "url": "Ue/blueprint/zh/PhysicsControl/AddControlstoSet.md"
        },
        {
            "name": "Create Body Modifier.md",
            "title": "Create Body Modifier.md",
            "depth": 4,
            "order": 5,
            "is_dir": false,
            "icon": "",
            "status": 1,
            "filepath": "Ue/blueprint/zh/Physics Control/Create Body Modifier.md",
            "url": "Ue/blueprint/zh/PhysicsControl/CreateBodyModifier.md"
        },
        {
            "name": "Create Body Modifiers from Limb Bones.md",
            "title": "Create Body Modifiers from Limb Bones.md",
            "depth": 4,
            "order": 6,
            "is_dir": false,
            "icon": "",
            "status": 1,
            "filepath": "Ue/blueprint/zh/Physics Control/Create Body Modifiers from Limb Bones.md",
            "url": "Ue/blueprint/zh/PhysicsControl/CreateBodyModifiersfromLimbBones.md"
        },
        {
            "name": "Create Body Modifiers from Skeletal Mesh Below.md",
            "title": "Create Body Modifiers from Skeletal Mesh Below.md",
            "depth": 4,
            "order": 7,
            "is_dir": false,
            "icon": "",
            "status": 1,
            "filepath": "Ue/blueprint/zh/Physics Control/Create Body Modifiers from Skeletal Mesh Below.md",
            "url": "Ue/blueprint/zh/PhysicsControl/CreateBodyModifiersfromSkeletalMeshBelow.md"
        },
        {
            "name": "Create Control.md",
            "title": "Create Control.md",
            "depth": 4,
            "order": 8,
            "is_dir": false,
            "icon": "",
            "status": 1,
            "filepath": "Ue/blueprint/zh/Physics Control/Create Control.md",
            "url": "Ue/blueprint/zh/PhysicsControl/CreateControl.md"
        },
        {
            "name": "Create Controls and Body Modifiers from Control Profile Asset.md",
            "title": "Create Controls and Body Modifiers from Control Profile Asset.md",
            "depth": 4,
            "order": 9,
            "is_dir": false,
            "icon": "",
            "status": 1,
            "filepath": "Ue/blueprint/zh/Physics Control/Create Controls and Body Modifiers from Control Profile Asset.md",
            "url": "Ue/blueprint/zh/PhysicsControl/CreateControlsandBodyModifiersfromControlProfileAsset.md"
        },
        {
            "name": "Create Controls and Body Modifiers from Limb Bones.md",
            "title": "Create Controls and Body Modifiers from Limb Bones.md",
            "depth": 4,
            "order": 10,
            "is_dir": false,
            "icon": "",
            "status": 1,
            "filepath": "Ue/blueprint/zh/Physics Control/Create Controls and Body Modifiers from Limb Bones.md",
            "url": "Ue/blueprint/zh/PhysicsControl/CreateControlsandBodyModifiersfromLimbBones.md"
        },
        {
            "name": "Create Controls from Limb Bones and Constraint Profile.md",
            "title": "Create Controls from Limb Bones and Constraint Profile.md",
            "depth": 4,
            "order": 11,
            "is_dir": false,
            "icon": "",
            "status": 1,
            "filepath": "Ue/blueprint/zh/Physics Control/Create Controls from Limb Bones and Constraint Profile.md",
            "url": "Ue/blueprint/zh/PhysicsControl/CreateControlsfromLimbBonesandConstraintProfile.md"
        },
        {
            "name": "Create Controls from Limb Bones.md",
            "title": "Create Controls from Limb Bones.md",
            "depth": 4,
            "order": 12,
            "is_dir": false,
            "icon": "",
            "status": 1,
            "filepath": "Ue/blueprint/zh/Physics Control/Create Controls from Limb Bones.md",
            "url": "Ue/blueprint/zh/PhysicsControl/CreateControlsfromLimbBones.md"
        },
        {
            "name": "Create Controls from Skeletal Mesh Below.md",
            "title": "Create Controls from Skeletal Mesh Below.md",
            "depth": 4,
            "order": 13,
            "is_dir": false,
            "icon": "",
            "status": 1,
            "filepath": "Ue/blueprint/zh/Physics Control/Create Controls from Skeletal Mesh Below.md",
            "url": "Ue/blueprint/zh/PhysicsControl/CreateControlsfromSkeletalMeshBelow.md"
        },
        {
            "name": "Create Controls from Skeletal Mesh and Constraint Profile Below.md",
            "title": "Create Controls from Skeletal Mesh and Constraint Profile Below.md",
            "depth": 4,
            "order": 14,
            "is_dir": false,
            "icon": "",
            "status": 1,
            "filepath": "Ue/blueprint/zh/Physics Control/Create Controls from Skeletal Mesh and Constraint Profile Below.md",
            "url": "Ue/blueprint/zh/PhysicsControl/CreateControlsfromSkeletalMeshandConstraintProfileBelow.md"
        },
        {
            "name": "Create Controls from Skeletal Mesh and Constraint Profile.md",
            "title": "Create Controls from Skeletal Mesh and Constraint Profile.md",
            "depth": 4,
            "order": 15,
            "is_dir": false,
            "icon": "",
            "status": 1,
            "filepath": "Ue/blueprint/zh/Physics Control/Create Controls from Skeletal Mesh and Constraint Profile.md",
            "url": "Ue/blueprint/zh/PhysicsControl/CreateControlsfromSkeletalMeshandConstraintProfile.md"
        },
        {
            "name": "Create Controls from Skeletal Mesh.md",
            "title": "Create Controls from Skeletal Mesh.md",
            "depth": 4,
            "order": 16,
            "is_dir": false,
            "icon": "",
            "status": 1,
            "filepath": "Ue/blueprint/zh/Physics Control/Create Controls from Skeletal Mesh.md",
            "url": "Ue/blueprint/zh/PhysicsControl/CreateControlsfromSkeletalMesh.md"
        },
        {
            "name": "Create Controls.md",
            "title": "Create Controls.md",
            "depth": 4,
            "order": 17,
            "is_dir": false,
            "icon": "",
            "status": 1,
            "filepath": "Ue/blueprint/zh/Physics Control/Create Controls.md",
            "url": "Ue/blueprint/zh/PhysicsControl/CreateControls.md"
        },
        {
            "name": "Create Named Body Modifier.md",
            "title": "Create Named Body Modifier.md",
            "depth": 4,
            "order": 18,
            "is_dir": false,
            "icon": "",
            "status": 1,
            "filepath": "Ue/blueprint/zh/Physics Control/Create Named Body Modifier.md",
            "url": "Ue/blueprint/zh/PhysicsControl/CreateNamedBodyModifier.md"
        },
        {
            "name": "Create Named Control.md",
            "title": "Create Named Control.md",
            "depth": 4,
            "order": 19,
            "is_dir": false,
            "icon": "",
            "status": 1,
            "filepath": "Ue/blueprint/zh/Physics Control/Create Named Control.md",
            "url": "Ue/blueprint/zh/PhysicsControl/CreateNamedControl.md"
        },
        {
            "name": "Destroy Body Modifier.md",
            "title": "Destroy Body Modifier.md",
            "depth": 4,
            "order": 20,
            "is_dir": false,
            "icon": "",
            "status": 1,
            "filepath": "Ue/blueprint/zh/Physics Control/Destroy Body Modifier.md",
            "url": "Ue/blueprint/zh/PhysicsControl/DestroyBodyModifier.md"
        },
        {
            "name": "Destroy Body Modifiers in Set.md",
            "title": "Destroy Body Modifiers in Set.md",
            "depth": 4,
            "order": 21,
            "is_dir": false,
            "icon": "",
            "status": 1,
            "filepath": "Ue/blueprint/zh/Physics Control/Destroy Body Modifiers in Set.md",
            "url": "Ue/blueprint/zh/PhysicsControl/DestroyBodyModifiersinSet.md"
        },
        {
            "name": "Destroy Body Modifiers.md",
            "title": "Destroy Body Modifiers.md",
            "depth": 4,
            "order": 22,
            "is_dir": false,
            "icon": "",
            "status": 1,
            "filepath": "Ue/blueprint/zh/Physics Control/Destroy Body Modifiers.md",
            "url": "Ue/blueprint/zh/PhysicsControl/DestroyBodyModifiers.md"
        },
        {
            "name": "Destroy Control.md",
            "title": "Destroy Control.md",
            "depth": 4,
            "order": 23,
            "is_dir": false,
            "icon": "",
            "status": 1,
            "filepath": "Ue/blueprint/zh/Physics Control/Destroy Control.md",
            "url": "Ue/blueprint/zh/PhysicsControl/DestroyControl.md"
        },
        {
            "name": "Destroy Controls in Set.md",
            "title": "Destroy Controls in Set.md",
            "depth": 4,
            "order": 24,
            "is_dir": false,
            "icon": "",
            "status": 1,
            "filepath": "Ue/blueprint/zh/Physics Control/Destroy Controls in Set.md",
            "url": "Ue/blueprint/zh/PhysicsControl/DestroyControlsinSet.md"
        },
        {
            "name": "Destroy Controls.md",
            "title": "Destroy Controls.md",
            "depth": 4,
            "order": 25,
            "is_dir": false,
            "icon": "",
            "status": 1,
            "filepath": "Ue/blueprint/zh/Physics Control/Destroy Controls.md",
            "url": "Ue/blueprint/zh/PhysicsControl/DestroyControls.md"
        },
        {
            "name": "Get All Body Modifier Names.md",
            "title": "Get All Body Modifier Names.md",
            "depth": 4,
            "order": 26,
            "is_dir": false,
            "icon": "",
            "status": 1,
            "filepath": "Ue/blueprint/zh/Physics Control/Get All Body Modifier Names.md",
            "url": "Ue/blueprint/zh/PhysicsControl/GetAllBodyModifierNames.md"
        },
        {
            "name": "Get All Control Names.md",
            "title": "Get All Control Names.md",
            "depth": 4,
            "order": 27,
            "is_dir": false,
            "icon": "",
            "status": 1,
            "filepath": "Ue/blueprint/zh/Physics Control/Get All Control Names.md",
            "url": "Ue/blueprint/zh/PhysicsControl/GetAllControlNames.md"
        },
        {
            "name": "Get Body Modifier Exists.md",
            "title": "Get Body Modifier Exists.md",
            "depth": 4,
            "order": 28,
            "is_dir": false,
            "icon": "",
            "status": 1,
            "filepath": "Ue/blueprint/zh/Physics Control/Get Body Modifier Exists.md",
            "url": "Ue/blueprint/zh/PhysicsControl/GetBodyModifierExists.md"
        },
        {
            "name": "Get Body Modifier Names in Set.md",
            "title": "Get Body Modifier Names in Set.md",
            "depth": 4,
            "order": 29,
            "is_dir": false,
            "icon": "",
            "status": 1,
            "filepath": "Ue/blueprint/zh/Physics Control/Get Body Modifier Names in Set.md",
            "url": "Ue/blueprint/zh/PhysicsControl/GetBodyModifierNamesinSet.md"
        },
        {
            "name": "Get Cached Bone Angular Velocities.md",
            "title": "Get Cached Bone Angular Velocities.md",
            "depth": 4,
            "order": 30,
            "is_dir": false,
            "icon": "",
            "status": 1,
            "filepath": "Ue/blueprint/zh/Physics Control/Get Cached Bone Angular Velocities.md",
            "url": "Ue/blueprint/zh/PhysicsControl/GetCachedBoneAngularVelocities.md"
        },
        {
            "name": "Get Cached Bone Angular Velocity.md",
            "title": "Get Cached Bone Angular Velocity.md",
            "depth": 4,
            "order": 31,
            "is_dir": false,
            "icon": "",
            "status": 1,
            "filepath": "Ue/blueprint/zh/Physics Control/Get Cached Bone Angular Velocity.md",
            "url": "Ue/blueprint/zh/PhysicsControl/GetCachedBoneAngularVelocity.md"
        },
        {
            "name": "Get Cached Bone Orientation.md",
            "title": "Get Cached Bone Orientation.md",
            "depth": 4,
            "order": 32,
            "is_dir": false,
            "icon": "",
            "status": 1,
            "filepath": "Ue/blueprint/zh/Physics Control/Get Cached Bone Orientation.md",
            "url": "Ue/blueprint/zh/PhysicsControl/GetCachedBoneOrientation.md"
        },
        {
            "name": "Get Cached Bone Orientations.md",
            "title": "Get Cached Bone Orientations.md",
            "depth": 4,
            "order": 33,
            "is_dir": false,
            "icon": "",
            "status": 1,
            "filepath": "Ue/blueprint/zh/Physics Control/Get Cached Bone Orientations.md",
            "url": "Ue/blueprint/zh/PhysicsControl/GetCachedBoneOrientations.md"
        },
        {
            "name": "Get Cached Bone Position.md",
            "title": "Get Cached Bone Position.md",
            "depth": 4,
            "order": 34,
            "is_dir": false,
            "icon": "",
            "status": 1,
            "filepath": "Ue/blueprint/zh/Physics Control/Get Cached Bone Position.md",
            "url": "Ue/blueprint/zh/PhysicsControl/GetCachedBonePosition.md"
        },
        {
            "name": "Get Cached Bone Positions.md",
            "title": "Get Cached Bone Positions.md",
            "depth": 4,
            "order": 35,
            "is_dir": false,
            "icon": "",
            "status": 1,
            "filepath": "Ue/blueprint/zh/Physics Control/Get Cached Bone Positions.md",
            "url": "Ue/blueprint/zh/PhysicsControl/GetCachedBonePositions.md"
        },
        {
            "name": "Get Cached Bone Transform.md",
            "title": "Get Cached Bone Transform.md",
            "depth": 4,
            "order": 36,
            "is_dir": false,
            "icon": "",
            "status": 1,
            "filepath": "Ue/blueprint/zh/Physics Control/Get Cached Bone Transform.md",
            "url": "Ue/blueprint/zh/PhysicsControl/GetCachedBoneTransform.md"
        },
        {
            "name": "Get Cached Bone Transforms.md",
            "title": "Get Cached Bone Transforms.md",
            "depth": 4,
            "order": 37,
            "is_dir": false,
            "icon": "",
            "status": 1,
            "filepath": "Ue/blueprint/zh/Physics Control/Get Cached Bone Transforms.md",
            "url": "Ue/blueprint/zh/PhysicsControl/GetCachedBoneTransforms.md"
        },
        {
            "name": "Get Cached Bone Velocities.md",
            "title": "Get Cached Bone Velocities.md",
            "depth": 4,
            "order": 38,
            "is_dir": false,
            "icon": "",
            "status": 1,
            "filepath": "Ue/blueprint/zh/Physics Control/Get Cached Bone Velocities.md",
            "url": "Ue/blueprint/zh/PhysicsControl/GetCachedBoneVelocities.md"
        },
        {
            "name": "Get Cached Bone Velocity.md",
            "title": "Get Cached Bone Velocity.md",
            "depth": 4,
            "order": 39,
            "is_dir": false,
            "icon": "",
            "status": 1,
            "filepath": "Ue/blueprint/zh/Physics Control/Get Cached Bone Velocity.md",
            "url": "Ue/blueprint/zh/PhysicsControl/GetCachedBoneVelocity.md"
        },
        {
            "name": "Get Control Data.md",
            "title": "Get Control Data.md",
            "depth": 4,
            "order": 40,
            "is_dir": false,
            "icon": "",
            "status": 1,
            "filepath": "Ue/blueprint/zh/Physics Control/Get Control Data.md",
            "url": "Ue/blueprint/zh/PhysicsControl/GetControlData.md"
        },
        {
            "name": "Get Control Enabled.md",
            "title": "Get Control Enabled.md",
            "depth": 4,
            "order": 41,
            "is_dir": false,
            "icon": "",
            "status": 1,
            "filepath": "Ue/blueprint/zh/Physics Control/Get Control Enabled.md",
            "url": "Ue/blueprint/zh/PhysicsControl/GetControlEnabled.md"
        },
        {
            "name": "Get Control Exists.md",
            "title": "Get Control Exists.md",
            "depth": 4,
            "order": 42,
            "is_dir": false,
            "icon": "",
            "status": 1,
            "filepath": "Ue/blueprint/zh/Physics Control/Get Control Exists.md",
            "url": "Ue/blueprint/zh/PhysicsControl/GetControlExists.md"
        },
        {
            "name": "Get Control Multiplier.md",
            "title": "Get Control Multiplier.md",
            "depth": 4,
            "order": 43,
            "is_dir": false,
            "icon": "",
            "status": 1,
            "filepath": "Ue/blueprint/zh/Physics Control/Get Control Multiplier.md",
            "url": "Ue/blueprint/zh/PhysicsControl/GetControlMultiplier.md"
        },
        {
            "name": "Get Control Names in Set.md",
            "title": "Get Control Names in Set.md",
            "depth": 4,
            "order": 44,
            "is_dir": false,
            "icon": "",
            "status": 1,
            "filepath": "Ue/blueprint/zh/Physics Control/Get Control Names in Set.md",
            "url": "Ue/blueprint/zh/PhysicsControl/GetControlNamesinSet.md"
        },
        {
            "name": "Get Control Target.md",
            "title": "Get Control Target.md",
            "depth": 4,
            "order": 45,
            "is_dir": false,
            "icon": "",
            "status": 1,
            "filepath": "Ue/blueprint/zh/Physics Control/Get Control Target.md",
            "url": "Ue/blueprint/zh/PhysicsControl/GetControlTarget.md"
        },
        {
            "name": "Get Limb Bones from Skeletal Mesh.md",
            "title": "Get Limb Bones from Skeletal Mesh.md",
            "depth": 4,
            "order": 46,
            "is_dir": false,
            "icon": "",
            "status": 1,
            "filepath": "Ue/blueprint/zh/Physics Control/Get Limb Bones from Skeletal Mesh.md",
            "url": "Ue/blueprint/zh/PhysicsControl/GetLimbBonesfromSkeletalMesh.md"
        },
        {
            "name": "Get Sets Containing Body Modifier.md",
            "title": "Get Sets Containing Body Modifier.md",
            "depth": 4,
            "order": 47,
            "is_dir": false,
            "icon": "",
            "status": 1,
            "filepath": "Ue/blueprint/zh/Physics Control/Get Sets Containing Body Modifier.md",
            "url": "Ue/blueprint/zh/PhysicsControl/GetSetsContainingBodyModifier.md"
        },
        {
            "name": "Get Sets Containing Control.md",
            "title": "Get Sets Containing Control.md",
            "depth": 4,
            "order": 48,
            "is_dir": false,
            "icon": "",
            "status": 1,
            "filepath": "Ue/blueprint/zh/Physics Control/Get Sets Containing Control.md",
            "url": "Ue/blueprint/zh/PhysicsControl/GetSetsContainingControl.md"
        },
        {
            "name": "Invoke Control Profile.md",
            "title": "Invoke Control Profile.md",
            "depth": 4,
            "order": 49,
            "is_dir": false,
            "icon": "",
            "status": 1,
            "filepath": "Ue/blueprint/zh/Physics Control/Invoke Control Profile.md",
            "url": "Ue/blueprint/zh/PhysicsControl/InvokeControlProfile.md"
        },
        {
            "name": "Reset Body Modifier to Cached Bone Transform.md",
            "title": "Reset Body Modifier to Cached Bone Transform.md",
            "depth": 4,
            "order": 50,
            "is_dir": false,
            "icon": "",
            "status": 1,
            "filepath": "Ue/blueprint/zh/Physics Control/Reset Body Modifier to Cached Bone Transform.md",
            "url": "Ue/blueprint/zh/PhysicsControl/ResetBodyModifiertoCachedBoneTransform.md"
        },
        {
            "name": "Reset Body Modifiers in Set to Cached Bone Transforms.md",
            "title": "Reset Body Modifiers in Set to Cached Bone Transforms.md",
            "depth": 4,
            "order": 51,
            "is_dir": false,
            "icon": "",
            "status": 1,
            "filepath": "Ue/blueprint/zh/Physics Control/Reset Body Modifiers in Set to Cached Bone Transforms.md",
            "url": "Ue/blueprint/zh/PhysicsControl/ResetBodyModifiersinSettoCachedBoneTransforms.md"
        },
        {
            "name": "Reset Body Modifiers to Cached Bone Transforms.md",
            "title": "Reset Body Modifiers to Cached Bone Transforms.md",
            "depth": 4,
            "order": 52,
            "is_dir": false,
            "icon": "",
            "status": 1,
            "filepath": "Ue/blueprint/zh/Physics Control/Reset Body Modifiers to Cached Bone Transforms.md",
            "url": "Ue/blueprint/zh/PhysicsControl/ResetBodyModifierstoCachedBoneTransforms.md"
        },
        {
            "name": "Reset Control Point.md",
            "title": "Reset Control Point.md",
            "depth": 4,
            "order": 53,
            "is_dir": false,
            "icon": "",
            "status": 1,
            "filepath": "Ue/blueprint/zh/Physics Control/Reset Control Point.md",
            "url": "Ue/blueprint/zh/PhysicsControl/ResetControlPoint.md"
        },
        {
            "name": "Set Body Modifier Collision Type.md",
            "title": "Set Body Modifier Collision Type.md",
            "depth": 4,
            "order": 54,
            "is_dir": false,
            "icon": "",
            "status": 1,
            "filepath": "Ue/blueprint/zh/Physics Control/Set Body Modifier Collision Type.md",
            "url": "Ue/blueprint/zh/PhysicsControl/SetBodyModifierCollisionType.md"
        },
        {
            "name": "Set Body Modifier Data.md",
            "title": "Set Body Modifier Data.md",
            "depth": 4,
            "order": 55,
            "is_dir": false,
            "icon": "",
            "status": 1,
            "filepath": "Ue/blueprint/zh/Physics Control/Set Body Modifier Data.md",
            "url": "Ue/blueprint/zh/PhysicsControl/SetBodyModifierData.md"
        },
        {
            "name": "Set Body Modifier Datas in Set.md",
            "title": "Set Body Modifier Datas in Set.md",
            "depth": 4,
            "order": 56,
            "is_dir": false,
            "icon": "",
            "status": 1,
            "filepath": "Ue/blueprint/zh/Physics Control/Set Body Modifier Datas in Set.md",
            "url": "Ue/blueprint/zh/PhysicsControl/SetBodyModifierDatasinSet.md"
        },
        {
            "name": "Set Body Modifier Datas.md",
            "title": "Set Body Modifier Datas.md",
            "depth": 4,
            "order": 57,
            "is_dir": false,
            "icon": "",
            "status": 1,
            "filepath": "Ue/blueprint/zh/Physics Control/Set Body Modifier Datas.md",
            "url": "Ue/blueprint/zh/PhysicsControl/SetBodyModifierDatas.md"
        },
        {
            "name": "Set Body Modifier Gravity Multiplier.md",
            "title": "Set Body Modifier Gravity Multiplier.md",
            "depth": 4,
            "order": 58,
            "is_dir": false,
            "icon": "",
            "status": 1,
            "filepath": "Ue/blueprint/zh/Physics Control/Set Body Modifier Gravity Multiplier.md",
            "url": "Ue/blueprint/zh/PhysicsControl/SetBodyModifierGravityMultiplier.md"
        },
        {
            "name": "Set Body Modifier Kinematic Target.md",
            "title": "Set Body Modifier Kinematic Target.md",
            "depth": 4,
            "order": 59,
            "is_dir": false,
            "icon": "",
            "status": 1,
            "filepath": "Ue/blueprint/zh/Physics Control/Set Body Modifier Kinematic Target.md",
            "url": "Ue/blueprint/zh/PhysicsControl/SetBodyModifierKinematicTarget.md"
        },
        {
            "name": "Set Body Modifier Movement Type.md",
            "title": "Set Body Modifier Movement Type.md",
            "depth": 4,
            "order": 60,
            "is_dir": false,
            "icon": "",
            "status": 1,
            "filepath": "Ue/blueprint/zh/Physics Control/Set Body Modifier Movement Type.md",
            "url": "Ue/blueprint/zh/PhysicsControl/SetBodyModifierMovementType.md"
        },
        {
            "name": "Set Body Modifier Physics Blend Weight.md",
            "title": "Set Body Modifier Physics Blend Weight.md",
            "depth": 4,
            "order": 61,
            "is_dir": false,
            "icon": "",
            "status": 1,
            "filepath": "Ue/blueprint/zh/Physics Control/Set Body Modifier Physics Blend Weight.md",
            "url": "Ue/blueprint/zh/PhysicsControl/SetBodyModifierPhysicsBlendWeight.md"
        },
        {
            "name": "Set Body Modifier Sparse Data.md",
            "title": "Set Body Modifier Sparse Data.md",
            "depth": 4,
            "order": 62,
            "is_dir": false,
            "icon": "",
            "status": 1,
            "filepath": "Ue/blueprint/zh/Physics Control/Set Body Modifier Sparse Data.md",
            "url": "Ue/blueprint/zh/PhysicsControl/SetBodyModifierSparseData.md"
        },
        {
            "name": "Set Body Modifier Sparse Datas in Set.md",
            "title": "Set Body Modifier Sparse Datas in Set.md",
            "depth": 4,
            "order": 63,
            "is_dir": false,
            "icon": "",
            "status": 1,
            "filepath": "Ue/blueprint/zh/Physics Control/Set Body Modifier Sparse Datas in Set.md",
            "url": "Ue/blueprint/zh/PhysicsControl/SetBodyModifierSparseDatasinSet.md"
        },
        {
            "name": "Set Body Modifier Sparse Datas.md",
            "title": "Set Body Modifier Sparse Datas.md",
            "depth": 4,
            "order": 64,
            "is_dir": false,
            "icon": "",
            "status": 1,
            "filepath": "Ue/blueprint/zh/Physics Control/Set Body Modifier Sparse Datas.md",
            "url": "Ue/blueprint/zh/PhysicsControl/SetBodyModifierSparseDatas.md"
        },
        {
            "name": "Set Body Modifier Update Kinematic from Simulation.md",
            "title": "Set Body Modifier Update Kinematic from Simulation.md",
            "depth": 4,
            "order": 65,
            "is_dir": false,
            "icon": "",
            "status": 1,
            "filepath": "Ue/blueprint/zh/Physics Control/Set Body Modifier Update Kinematic from Simulation.md",
            "url": "Ue/blueprint/zh/PhysicsControl/SetBodyModifierUpdateKinematicfromSimulation.md"
        },
        {
            "name": "Set Body Modifier Use Skeletal Animation.md",
            "title": "Set Body Modifier Use Skeletal Animation.md",
            "depth": 4,
            "order": 66,
            "is_dir": false,
            "icon": "",
            "status": 1,
            "filepath": "Ue/blueprint/zh/Physics Control/Set Body Modifier Use Skeletal Animation.md",
            "url": "Ue/blueprint/zh/PhysicsControl/SetBodyModifierUseSkeletalAnimation.md"
        },
        {
            "name": "Set Body Modifiers Collision Type.md",
            "title": "Set Body Modifiers Collision Type.md",
            "depth": 4,
            "order": 67,
            "is_dir": false,
            "icon": "",
            "status": 1,
            "filepath": "Ue/blueprint/zh/Physics Control/Set Body Modifiers Collision Type.md",
            "url": "Ue/blueprint/zh/PhysicsControl/SetBodyModifiersCollisionType.md"
        },
        {
            "name": "Set Body Modifiers Gravity Multiplier.md",
            "title": "Set Body Modifiers Gravity Multiplier.md",
            "depth": 4,
            "order": 68,
            "is_dir": false,
            "icon": "",
            "status": 1,
            "filepath": "Ue/blueprint/zh/Physics Control/Set Body Modifiers Gravity Multiplier.md",
            "url": "Ue/blueprint/zh/PhysicsControl/SetBodyModifiersGravityMultiplier.md"
        },
        {
            "name": "Set Body Modifiers Movement Type.md",
            "title": "Set Body Modifiers Movement Type.md",
            "depth": 4,
            "order": 69,
            "is_dir": false,
            "icon": "",
            "status": 1,
            "filepath": "Ue/blueprint/zh/Physics Control/Set Body Modifiers Movement Type.md",
            "url": "Ue/blueprint/zh/PhysicsControl/SetBodyModifiersMovementType.md"
        },
        {
            "name": "Set Body Modifiers Physics Blend Weight.md",
            "title": "Set Body Modifiers Physics Blend Weight.md",
            "depth": 4,
            "order": 70,
            "is_dir": false,
            "icon": "",
            "status": 1,
            "filepath": "Ue/blueprint/zh/Physics Control/Set Body Modifiers Physics Blend Weight.md",
            "url": "Ue/blueprint/zh/PhysicsControl/SetBodyModifiersPhysicsBlendWeight.md"
        },
        {
            "name": "Set Body Modifiers Update Kinematic from Simulation.md",
            "title": "Set Body Modifiers Update Kinematic from Simulation.md",
            "depth": 4,
            "order": 71,
            "is_dir": false,
            "icon": "",
            "status": 1,
            "filepath": "Ue/blueprint/zh/Physics Control/Set Body Modifiers Update Kinematic from Simulation.md",
            "url": "Ue/blueprint/zh/PhysicsControl/SetBodyModifiersUpdateKinematicfromSimulation.md"
        },
        {
            "name": "Set Body Modifiers Use Skeletal Animation.md",
            "title": "Set Body Modifiers Use Skeletal Animation.md",
            "depth": 4,
            "order": 72,
            "is_dir": false,
            "icon": "",
            "status": 1,
            "filepath": "Ue/blueprint/zh/Physics Control/Set Body Modifiers Use Skeletal Animation.md",
            "url": "Ue/blueprint/zh/PhysicsControl/SetBodyModifiersUseSkeletalAnimation.md"
        },
        {
            "name": "Set Body Modifiers in Set Collision Type.md",
            "title": "Set Body Modifiers in Set Collision Type.md",
            "depth": 4,
            "order": 73,
            "is_dir": false,
            "icon": "",
            "status": 1,
            "filepath": "Ue/blueprint/zh/Physics Control/Set Body Modifiers in Set Collision Type.md",
            "url": "Ue/blueprint/zh/PhysicsControl/SetBodyModifiersinSetCollisionType.md"
        },
        {
            "name": "Set Body Modifiers in Set Gravity Multiplier.md",
            "title": "Set Body Modifiers in Set Gravity Multiplier.md",
            "depth": 4,
            "order": 74,
            "is_dir": false,
            "icon": "",
            "status": 1,
            "filepath": "Ue/blueprint/zh/Physics Control/Set Body Modifiers in Set Gravity Multiplier.md",
            "url": "Ue/blueprint/zh/PhysicsControl/SetBodyModifiersinSetGravityMultiplier.md"
        },
        {
            "name": "Set Body Modifiers in Set Movement Type.md",
            "title": "Set Body Modifiers in Set Movement Type.md",
            "depth": 4,
            "order": 75,
            "is_dir": false,
            "icon": "",
            "status": 1,
            "filepath": "Ue/blueprint/zh/Physics Control/Set Body Modifiers in Set Movement Type.md",
            "url": "Ue/blueprint/zh/PhysicsControl/SetBodyModifiersinSetMovementType.md"
        },
        {
            "name": "Set Body Modifiers in Set Physics Blend Weight.md",
            "title": "Set Body Modifiers in Set Physics Blend Weight.md",
            "depth": 4,
            "order": 76,
            "is_dir": false,
            "icon": "",
            "status": 1,
            "filepath": "Ue/blueprint/zh/Physics Control/Set Body Modifiers in Set Physics Blend Weight.md",
            "url": "Ue/blueprint/zh/PhysicsControl/SetBodyModifiersinSetPhysicsBlendWeight.md"
        },
        {
            "name": "Set Body Modifiers in Set Update Kinematic from Simulation.md",
            "title": "Set Body Modifiers in Set Update Kinematic from Simulation.md",
            "depth": 4,
            "order": 77,
            "is_dir": false,
            "icon": "",
            "status": 1,
            "filepath": "Ue/blueprint/zh/Physics Control/Set Body Modifiers in Set Update Kinematic from Simulation.md",
            "url": "Ue/blueprint/zh/PhysicsControl/SetBodyModifiersinSetUpdateKinematicfromSimulation.md"
        },
        {
            "name": "Set Body Modifiers in Set Use Skeletal Animation.md",
            "title": "Set Body Modifiers in Set Use Skeletal Animation.md",
            "depth": 4,
            "order": 78,
            "is_dir": false,
            "icon": "",
            "status": 1,
            "filepath": "Ue/blueprint/zh/Physics Control/Set Body Modifiers in Set Use Skeletal Animation.md",
            "url": "Ue/blueprint/zh/PhysicsControl/SetBodyModifiersinSetUseSkeletalAnimation.md"
        },
        {
            "name": "Set Cached Bone Data.md",
            "title": "Set Cached Bone Data.md",
            "depth": 4,
            "order": 79,
            "is_dir": false,
            "icon": "",
            "status": 1,
            "filepath": "Ue/blueprint/zh/Physics Control/Set Cached Bone Data.md",
            "url": "Ue/blueprint/zh/PhysicsControl/SetCachedBoneData.md"
        },
        {
            "name": "Set Control Angular Data.md",
            "title": "Set Control Angular Data.md",
            "depth": 4,
            "order": 80,
            "is_dir": false,
            "icon": "",
            "status": 1,
            "filepath": "Ue/blueprint/zh/Physics Control/Set Control Angular Data.md",
            "url": "Ue/blueprint/zh/PhysicsControl/SetControlAngularData.md"
        },
        {
            "name": "Set Control Data.md",
            "title": "Set Control Data.md",
            "depth": 4,
            "order": 81,
            "is_dir": false,
            "icon": "",
            "status": 1,
            "filepath": "Ue/blueprint/zh/Physics Control/Set Control Data.md",
            "url": "Ue/blueprint/zh/PhysicsControl/SetControlData.md"
        },
        {
            "name": "Set Control Datas in Set.md",
            "title": "Set Control Datas in Set.md",
            "depth": 4,
            "order": 82,
            "is_dir": false,
            "icon": "",
            "status": 1,
            "filepath": "Ue/blueprint/zh/Physics Control/Set Control Datas in Set.md",
            "url": "Ue/blueprint/zh/PhysicsControl/SetControlDatasinSet.md"
        },
        {
            "name": "Set Control Datas.md",
            "title": "Set Control Datas.md",
            "depth": 4,
            "order": 83,
            "is_dir": false,
            "icon": "",
            "status": 1,
            "filepath": "Ue/blueprint/zh/Physics Control/Set Control Datas.md",
            "url": "Ue/blueprint/zh/PhysicsControl/SetControlDatas.md"
        },
        {
            "name": "Set Control Disable Collision.md",
            "title": "Set Control Disable Collision.md",
            "depth": 4,
            "order": 84,
            "is_dir": false,
            "icon": "",
            "status": 1,
            "filepath": "Ue/blueprint/zh/Physics Control/Set Control Disable Collision.md",
            "url": "Ue/blueprint/zh/PhysicsControl/SetControlDisableCollision.md"
        },
        {
            "name": "Set Control Enabled.md",
            "title": "Set Control Enabled.md",
            "depth": 4,
            "order": 85,
            "is_dir": false,
            "icon": "",
            "status": 1,
            "filepath": "Ue/blueprint/zh/Physics Control/Set Control Enabled.md",
            "url": "Ue/blueprint/zh/PhysicsControl/SetControlEnabled.md"
        },
        {
            "name": "Set Control Linear Data.md",
            "title": "Set Control Linear Data.md",
            "depth": 4,
            "order": 86,
            "is_dir": false,
            "icon": "",
            "status": 1,
            "filepath": "Ue/blueprint/zh/Physics Control/Set Control Linear Data.md",
            "url": "Ue/blueprint/zh/PhysicsControl/SetControlLinearData.md"
        },
        {
            "name": "Set Control Multiplier.md",
            "title": "Set Control Multiplier.md",
            "depth": 4,
            "order": 87,
            "is_dir": false,
            "icon": "",
            "status": 1,
            "filepath": "Ue/blueprint/zh/Physics Control/Set Control Multiplier.md",
            "url": "Ue/blueprint/zh/PhysicsControl/SetControlMultiplier.md"
        },
        {
            "name": "Set Control Multipliers in Set.md",
            "title": "Set Control Multipliers in Set.md",
            "depth": 4,
            "order": 88,
            "is_dir": false,
            "icon": "",
            "status": 1,
            "filepath": "Ue/blueprint/zh/Physics Control/Set Control Multipliers in Set.md",
            "url": "Ue/blueprint/zh/PhysicsControl/SetControlMultipliersinSet.md"
        },
        {
            "name": "Set Control Multipliers.md",
            "title": "Set Control Multipliers.md",
            "depth": 4,
            "order": 89,
            "is_dir": false,
            "icon": "",
            "status": 1,
            "filepath": "Ue/blueprint/zh/Physics Control/Set Control Multipliers.md",
            "url": "Ue/blueprint/zh/PhysicsControl/SetControlMultipliers.md"
        },
        {
            "name": "Set Control Parent.md",
            "title": "Set Control Parent.md",
            "depth": 4,
            "order": 90,
            "is_dir": false,
            "icon": "",
            "status": 1,
            "filepath": "Ue/blueprint/zh/Physics Control/Set Control Parent.md",
            "url": "Ue/blueprint/zh/PhysicsControl/SetControlParent.md"
        },
        {
            "name": "Set Control Parents in Set.md",
            "title": "Set Control Parents in Set.md",
            "depth": 4,
            "order": 91,
            "is_dir": false,
            "icon": "",
            "status": 1,
            "filepath": "Ue/blueprint/zh/Physics Control/Set Control Parents in Set.md",
            "url": "Ue/blueprint/zh/PhysicsControl/SetControlParentsinSet.md"
        },
        {
            "name": "Set Control Parents.md",
            "title": "Set Control Parents.md",
            "depth": 4,
            "order": 92,
            "is_dir": false,
            "icon": "",
            "status": 1,
            "filepath": "Ue/blueprint/zh/Physics Control/Set Control Parents.md",
            "url": "Ue/blueprint/zh/PhysicsControl/SetControlParents.md"
        },
        {
            "name": "Set Control Point.md",
            "title": "Set Control Point.md",
            "depth": 4,
            "order": 93,
            "is_dir": false,
            "icon": "",
            "status": 1,
            "filepath": "Ue/blueprint/zh/Physics Control/Set Control Point.md",
            "url": "Ue/blueprint/zh/PhysicsControl/SetControlPoint.md"
        },
        {
            "name": "Set Control Sparse Data.md",
            "title": "Set Control Sparse Data.md",
            "depth": 4,
            "order": 94,
            "is_dir": false,
            "icon": "",
            "status": 1,
            "filepath": "Ue/blueprint/zh/Physics Control/Set Control Sparse Data.md",
            "url": "Ue/blueprint/zh/PhysicsControl/SetControlSparseData.md"
        },
        {
            "name": "Set Control Sparse Datas in Set.md",
            "title": "Set Control Sparse Datas in Set.md",
            "depth": 4,
            "order": 95,
            "is_dir": false,
            "icon": "",
            "status": 1,
            "filepath": "Ue/blueprint/zh/Physics Control/Set Control Sparse Datas in Set.md",
            "url": "Ue/blueprint/zh/PhysicsControl/SetControlSparseDatasinSet.md"
        },
        {
            "name": "Set Control Sparse Datas.md",
            "title": "Set Control Sparse Datas.md",
            "depth": 4,
            "order": 96,
            "is_dir": false,
            "icon": "",
            "status": 1,
            "filepath": "Ue/blueprint/zh/Physics Control/Set Control Sparse Datas.md",
            "url": "Ue/blueprint/zh/PhysicsControl/SetControlSparseDatas.md"
        },
        {
            "name": "Set Control Sparse Multiplier.md",
            "title": "Set Control Sparse Multiplier.md",
            "depth": 4,
            "order": 97,
            "is_dir": false,
            "icon": "",
            "status": 1,
            "filepath": "Ue/blueprint/zh/Physics Control/Set Control Sparse Multiplier.md",
            "url": "Ue/blueprint/zh/PhysicsControl/SetControlSparseMultiplier.md"
        },
        {
            "name": "Set Control Sparse Multipliers in Set.md",
            "title": "Set Control Sparse Multipliers in Set.md",
            "depth": 4,
            "order": 98,
            "is_dir": false,
            "icon": "",
            "status": 1,
            "filepath": "Ue/blueprint/zh/Physics Control/Set Control Sparse Multipliers in Set.md",
            "url": "Ue/blueprint/zh/PhysicsControl/SetControlSparseMultipliersinSet.md"
        },
        {
            "name": "Set Control Sparse Multipliers.md",
            "title": "Set Control Sparse Multipliers.md",
            "depth": 4,
            "order": 99,
            "is_dir": false,
            "icon": "",
            "status": 1,
            "filepath": "Ue/blueprint/zh/Physics Control/Set Control Sparse Multipliers.md",
            "url": "Ue/blueprint/zh/PhysicsControl/SetControlSparseMultipliers.md"
        },
        {
            "name": "Set Control Target Orientation.md",
            "title": "Set Control Target Orientation.md",
            "depth": 4,
            "order": 100,
            "is_dir": false,
            "icon": "",
            "status": 1,
            "filepath": "Ue/blueprint/zh/Physics Control/Set Control Target Orientation.md",
            "url": "Ue/blueprint/zh/PhysicsControl/SetControlTargetOrientation.md"
        },
        {
            "name": "Set Control Target Orientations from Array.md",
            "title": "Set Control Target Orientations from Array.md",
            "depth": 4,
            "order": 101,
            "is_dir": false,
            "icon": "",
            "status": 1,
            "filepath": "Ue/blueprint/zh/Physics Control/Set Control Target Orientations from Array.md",
            "url": "Ue/blueprint/zh/PhysicsControl/SetControlTargetOrientationsfromArray.md"
        },
        {
            "name": "Set Control Target Orientations in Set.md",
            "title": "Set Control Target Orientations in Set.md",
            "depth": 4,
            "order": 102,
            "is_dir": false,
            "icon": "",
            "status": 1,
            "filepath": "Ue/blueprint/zh/Physics Control/Set Control Target Orientations in Set.md",
            "url": "Ue/blueprint/zh/PhysicsControl/SetControlTargetOrientationsinSet.md"
        },
        {
            "name": "Set Control Target Orientations.md",
            "title": "Set Control Target Orientations.md",
            "depth": 4,
            "order": 103,
            "is_dir": false,
            "icon": "",
            "status": 1,
            "filepath": "Ue/blueprint/zh/Physics Control/Set Control Target Orientations.md",
            "url": "Ue/blueprint/zh/PhysicsControl/SetControlTargetOrientations.md"
        },
        {
            "name": "Set Control Target Poses.md",
            "title": "Set Control Target Poses.md",
            "depth": 4,
            "order": 104,
            "is_dir": false,
            "icon": "",
            "status": 1,
            "filepath": "Ue/blueprint/zh/Physics Control/Set Control Target Poses.md",
            "url": "Ue/blueprint/zh/PhysicsControl/SetControlTargetPoses.md"
        },
        {
            "name": "Set Control Target Position and Orientation.md",
            "title": "Set Control Target Position and Orientation.md",
            "depth": 4,
            "order": 105,
            "is_dir": false,
            "icon": "",
            "status": 1,
            "filepath": "Ue/blueprint/zh/Physics Control/Set Control Target Position and Orientation.md",
            "url": "Ue/blueprint/zh/PhysicsControl/SetControlTargetPositionandOrientation.md"
        },
        {
            "name": "Set Control Target Position.md",
            "title": "Set Control Target Position.md",
            "depth": 4,
            "order": 106,
            "is_dir": false,
            "icon": "",
            "status": 1,
            "filepath": "Ue/blueprint/zh/Physics Control/Set Control Target Position.md",
            "url": "Ue/blueprint/zh/PhysicsControl/SetControlTargetPosition.md"
        },
        {
            "name": "Set Control Target Positions and Orientations from Array.md",
            "title": "Set Control Target Positions and Orientations from Array.md",
            "depth": 4,
            "order": 107,
            "is_dir": false,
            "icon": "",
            "status": 1,
            "filepath": "Ue/blueprint/zh/Physics Control/Set Control Target Positions and Orientations from Array.md",
            "url": "Ue/blueprint/zh/PhysicsControl/SetControlTargetPositionsandOrientationsfromArray.md"
        },
        {
            "name": "Set Control Target Positions and Orientations in Set.md",
            "title": "Set Control Target Positions and Orientations in Set.md",
            "depth": 4,
            "order": 108,
            "is_dir": false,
            "icon": "",
            "status": 1,
            "filepath": "Ue/blueprint/zh/Physics Control/Set Control Target Positions and Orientations in Set.md",
            "url": "Ue/blueprint/zh/PhysicsControl/SetControlTargetPositionsandOrientationsinSet.md"
        },
        {
            "name": "Set Control Target Positions and Orientations.md",
            "title": "Set Control Target Positions and Orientations.md",
            "depth": 4,
            "order": 109,
            "is_dir": false,
            "icon": "",
            "status": 1,
            "filepath": "Ue/blueprint/zh/Physics Control/Set Control Target Positions and Orientations.md",
            "url": "Ue/blueprint/zh/PhysicsControl/SetControlTargetPositionsandOrientations.md"
        },
        {
            "name": "Set Control Target Positions from Array.md",
            "title": "Set Control Target Positions from Array.md",
            "depth": 4,
            "order": 110,
            "is_dir": false,
            "icon": "",
            "status": 1,
            "filepath": "Ue/blueprint/zh/Physics Control/Set Control Target Positions from Array.md",
            "url": "Ue/blueprint/zh/PhysicsControl/SetControlTargetPositionsfromArray.md"
        },
        {
            "name": "Set Control Target Positions in Set.md",
            "title": "Set Control Target Positions in Set.md",
            "depth": 4,
            "order": 111,
            "is_dir": false,
            "icon": "",
            "status": 1,
            "filepath": "Ue/blueprint/zh/Physics Control/Set Control Target Positions in Set.md",
            "url": "Ue/blueprint/zh/PhysicsControl/SetControlTargetPositionsinSet.md"
        },
        {
            "name": "Set Control Target Positions.md",
            "title": "Set Control Target Positions.md",
            "depth": 4,
            "order": 112,
            "is_dir": false,
            "icon": "",
            "status": 1,
            "filepath": "Ue/blueprint/zh/Physics Control/Set Control Target Positions.md",
            "url": "Ue/blueprint/zh/PhysicsControl/SetControlTargetPositions.md"
        },
        {
            "name": "Set Control Target.md",
            "title": "Set Control Target.md",
            "depth": 4,
            "order": 113,
            "is_dir": false,
            "icon": "",
            "status": 1,
            "filepath": "Ue/blueprint/zh/Physics Control/Set Control Target.md",
            "url": "Ue/blueprint/zh/PhysicsControl/SetControlTarget.md"
        },
        {
            "name": "Set Control Targets in Set.md",
            "title": "Set Control Targets in Set.md",
            "depth": 4,
            "order": 114,
            "is_dir": false,
            "icon": "",
            "status": 1,
            "filepath": "Ue/blueprint/zh/Physics Control/Set Control Targets in Set.md",
            "url": "Ue/blueprint/zh/PhysicsControl/SetControlTargetsinSet.md"
        },
        {
            "name": "Set Control Targets.md",
            "title": "Set Control Targets.md",
            "depth": 4,
            "order": 115,
            "is_dir": false,
            "icon": "",
            "status": 1,
            "filepath": "Ue/blueprint/zh/Physics Control/Set Control Targets.md",
            "url": "Ue/blueprint/zh/PhysicsControl/SetControlTargets.md"
        },
        {
            "name": "Set Control Use Skeletal Animation.md",
            "title": "Set Control Use Skeletal Animation.md",
            "depth": 4,
            "order": 116,
            "is_dir": false,
            "icon": "",
            "status": 1,
            "filepath": "Ue/blueprint/zh/Physics Control/Set Control Use Skeletal Animation.md",
            "url": "Ue/blueprint/zh/PhysicsControl/SetControlUseSkeletalAnimation.md"
        },
        {
            "name": "Set Controls Disable Collision.md",
            "title": "Set Controls Disable Collision.md",
            "depth": 4,
            "order": 117,
            "is_dir": false,
            "icon": "",
            "status": 1,
            "filepath": "Ue/blueprint/zh/Physics Control/Set Controls Disable Collision.md",
            "url": "Ue/blueprint/zh/PhysicsControl/SetControlsDisableCollision.md"
        },
        {
            "name": "Set Controls Enabled.md",
            "title": "Set Controls Enabled.md",
            "depth": 4,
            "order": 118,
            "is_dir": false,
            "icon": "",
            "status": 1,
            "filepath": "Ue/blueprint/zh/Physics Control/Set Controls Enabled.md",
            "url": "Ue/blueprint/zh/PhysicsControl/SetControlsEnabled.md"
        },
        {
            "name": "Set Controls Use Skeletal Animation.md",
            "title": "Set Controls Use Skeletal Animation.md",
            "depth": 4,
            "order": 119,
            "is_dir": false,
            "icon": "",
            "status": 1,
            "filepath": "Ue/blueprint/zh/Physics Control/Set Controls Use Skeletal Animation.md",
            "url": "Ue/blueprint/zh/PhysicsControl/SetControlsUseSkeletalAnimation.md"
        },
        {
            "name": "Set Controls in Set Disable Collision.md",
            "title": "Set Controls in Set Disable Collision.md",
            "depth": 4,
            "order": 120,
            "is_dir": false,
            "icon": "",
            "status": 1,
            "filepath": "Ue/blueprint/zh/Physics Control/Set Controls in Set Disable Collision.md",
            "url": "Ue/blueprint/zh/PhysicsControl/SetControlsinSetDisableCollision.md"
        },
        {
            "name": "Set Controls in Set Enabled.md",
            "title": "Set Controls in Set Enabled.md",
            "depth": 4,
            "order": 121,
            "is_dir": false,
            "icon": "",
            "status": 1,
            "filepath": "Ue/blueprint/zh/Physics Control/Set Controls in Set Enabled.md",
            "url": "Ue/blueprint/zh/PhysicsControl/SetControlsinSetEnabled.md"
        },
        {
            "name": "Set Controls in Set Use Skeletal Animation.md",
            "title": "Set Controls in Set Use Skeletal Animation.md",
            "depth": 4,
            "order": 122,
            "is_dir": false,
            "icon": "",
            "status": 1,
            "filepath": "Ue/blueprint/zh/Physics Control/Set Controls in Set Use Skeletal Animation.md",
            "url": "Ue/blueprint/zh/PhysicsControl/SetControlsinSetUseSkeletalAnimation.md"
        },
        {
            "name": "Update Controls.md",
            "title": "Update Controls.md",
            "depth": 4,
            "order": 123,
            "is_dir": false,
            "icon": "",
            "status": 1,
            "filepath": "Ue/blueprint/zh/Physics Control/Update Controls.md",
            "url": "Ue/blueprint/zh/PhysicsControl/UpdateControls.md"
        },
        {
            "name": "Update Target Caches.md",
            "title": "Update Target Caches.md",
            "depth": 4,
            "order": 124,
            "is_dir": false,
            "icon": "",
            "status": 1,
            "filepath": "Ue/blueprint/zh/Physics Control/Update Target Caches.md",
            "url": "Ue/blueprint/zh/PhysicsControl/UpdateTargetCaches.md"
        }
    ],
    "categorys": []
}